{"nodes": [{"id": "UgxunD7KgIvZaUnJunN4AaABAg", "text": "6:33 이거보고 막내가 있어야 집안이 화목해진다는 말 믿기로함", "likeCount": 624, "sentiment": "POSITIVE", "topic": "막내 귀여움", "x": 104.6767349243164, "y": -17.535364151000977, "z": -50.24992752075195, "x2d": 95.99504852294922, "y2d": 28.652301788330078}, {"id": "UgwxPcNmL1joxXd6SoF4AaABAg", "text": "막내 졸귀력 미쳣네 진짜ㅋㅋㅋㅋ", "likeCount": 371, "sentiment": "POSITIVE", "topic": "막내 귀여움", "x": 116.3156509399414, "y": -91.62481689453125, "z": 35.942466735839844, "x2d": 117.94461822509766, "y2d": 115.45620727539062}, {"id": "Ugz_2FS16-tAw21maaN4AaABAg", "text": "3:44 아 막내님 방싯방싯하면서 미소 연습하는거 진짜 귀엽다", "likeCount": 338, "sentiment": "POSITIVE", "topic": "막내 귀여움", "x": 148.4150390625, "y": -78.62175750732422, "z": -28.64605140686035, "x2d": 143.8518829345703, "y2d": 68.88569641113281}, {"id": "UgyVJsJ-bJ-S9AiuLzJ4AaABAg", "text": "6:45 수환ㅋㅋ다리는 왜 떠는건데 아웃겨 미치겠다", "likeCount": 256, "sentiment": "POSITIVE", "topic": "막내 귀여움", "x": 92.60604858398438, "y": 51.688926696777344, "z": -54.92741775512695, "x2d": 75.11857604980469, "y2d": -0.7538991570472717}, {"id": "Ugw4fmlkj69-u3E4MsB4AaABAg", "text": "아 막내 재롱에 숨넘어가는 행님들ㅋㅋㅋㅋㅋㅋㅋㅋㅋ", "likeCount": 216, "sentiment": "POSITIVE", "topic": "막내 귀여움", "x": 67.82218933105469, "y": -33.77839279174805, "z": -65.022216796875, "x2d": 89.38715362548828, "y2d": -79.28189849853516}, {"id": "UgwKb5EX3cKi5QTzQ_J4AaABAg", "text": "6:19 뚝딱이는 수환이 넘 커여운데ㅋㅋㅋㅋ", "likeCount": 171, "sentiment": "POSITIVE", "topic": "막내 귀여움", "x": 96.20360565185547, "y": 103.52995300292969, "z": -23.20920181274414, "x2d": 80.76026916503906, "y2d": 33.866661071777344}, {"id": "Ugx5eF-zgJDyinSqmOp4AaABAg", "text": "4:14 ㅋㅋㅋㅋㅋㅋㅋㅋㅋㅋ귀여웤ㅋㅋㅋ", "likeCount": 162, "sentiment": "POSITIVE", "topic": "막내 귀여움", "x": 146.2506103515625, "y": -37.821773529052734, "z": -90.26203155517578, "x2d": 119.49166107177734, "y2d": 3.0699450969696045}, {"id": "UgxeHRPXsYpYwrZggVl4AaABAg", "text": "수환이 그낭 진짜 아가네ㅋㅋㅋㅋㅋㅋ개웃곀ㅋㅋㅋㅋㅋㅋ이때는 아직 볼살이 통통해서 더 귀엽네", "likeCount": 147, "sentiment": "POSITIVE", "topic": "막내 귀여움", "x": 116.0107192993164, "y": -6.066630840301514, "z": 59.949066162109375, "x2d": 92.11800384521484, "y2d": 119.00016784667969}, {"id": "Ugy7amkPZzWn50A_74t4AaABAg", "text": "6:13 란도 웃는거 넘 귀욥", "likeCount": 143, "sentiment": "POSITIVE", "topic": "막내 귀여움", "x": 130.5099639892578, "y": 21.088260650634766, "z": -44.57923126220703, "x2d": 118.8906478881836, "y2d": 26.152545928955078}, {"id": "UgyhWCw8aB02GXZBEX54AaABAg", "text": "6:33 하..귀여워 미쳐버리겠네", "likeCount": 129, "sentiment": "POSITIVE", "topic": "막내 귀여움", "x": 138.63601684570312, "y": -33.50850296020508, "z": -62.06846237182617, "x2d": 139.41976928710938, "y2d": 21.755828857421875}, {"id": "UgwhGnW_LZHu9-lh9mp4AaABAg", "text": "6:54 엉거주춤 도련님과 숨넘어 가는 오랑이 ㅎㅎ", "likeCount": 128, "sentiment": "POSITIVE", "topic": "막내 귀여움", "x": 60.29209518432617, "y": 73.10047149658203, "z": -59.719696044921875, "x2d": 49.4571533203125, "y2d": -45.44499969482422}, {"id": "Ugy6MD04XwudtCRotnR4AaABAg", "text": "6:43 막내의 개다리춤 재롱ㅋㅋㅋㅋ", "likeCount": 114, "sentiment": "POSITIVE", "topic": "막내 귀여움", "x": 74.88265991210938, "y": 1.2125955820083618, "z": -64.83185577392578, "x2d": 77.47795104980469, "y2d": -37.06089401245117}, {"id": "UgxtFYaajII_TNZLUIN4AaABAg", "text": "솬이 진짜 개귀엽네 ㅋㅋㅋㅋㅋㅋㅋ", "likeCount": 92, "sentiment": "POSITIVE", "topic": "막내 귀여움", "x": 81.84150695800781, "y": -71.88074493408203, "z": 72.89872741699219, "x2d": 54.3286247253418, "y2d": 160.1082763671875}, {"id": "UgyRrNPg5G2fCNda2s54AaABAg", "text": "6:13 란도 넘 귀여워 ㅜㅜ", "likeCount": 77, "sentiment": "POSITIVE", "topic": "막내 귀여움", "x": 147.87501525878906, "y": -20.268600463867188, "z": -55.809898376464844, "x2d": 138.0786895751953, "y2d": 37.47996520996094}, {"id": "UgyDH2i_ZLQaXbQrqvl4AaABAg", "text": "웃는 거 연습하는 코알라 실존 뭐임\n막내라는 거 진짜 좋다..귀엽다.......", "likeCount": 77, "sentiment": "POSITIVE", "topic": "막내 귀여움", "x": 140.26968383789062, "y": -89.8262939453125, "z": 9.896717071533203, "x2d": 141.07662963867188, "y2d": 97.03086853027344}, {"id": "UgwaKNozKvLPNxQigKF4AaABAg", "text": "5:40 ㅋㅋㅋㅋ수환이ㅌㅋㅋㅋㅋㅋㅋㅋㅋㅋㅋㅋ귀엽네", "likeCount": 75, "sentiment": "POSITIVE", "topic": "막내 귀여움", "x": 139.23255920410156, "y": 36.87525177001953, "z": -27.692800521850586, "x2d": 107.21627044677734, "y2d": 28.26694679260254}, {"id": "UgyL36JM5mc__ZHz-YZ4AaABAg", "text": "6:55 ㅋㅋㅋㅋㅋㅋㅋㅋㅋ수환이 자세ㅋㅋㅋㅋㅋㅋㅋ", "likeCount": 57, "sentiment": "POSITIVE", "topic": "막내 귀여움", "x": 98.95877838134766, "y": 97.92362213134766, "z": 11.32278823852539, "x2d": 63.53467559814453, "y2d": 47.3773193359375}, {"id": "UgyO4raLZ6n8L8MheoR4AaABAg", "text": "04:02 우리혁 잔소리 귀하다..", "likeCount": 55, "sentiment": "POSITIVE", "topic": "막내 귀여움", "x": 161.6946258544922, "y": -70.79107666015625, "z": -73.1092300415039, "x2d": 141.4996795654297, "y2d": -4.301153182983398}, {"id": "UgzNkblaPFroQGebaD54AaABAg", "text": "6:08 양손 주먹 꽉쥐고 흔들흔들 귀엽네\n6:19 고장난 로봇도 개웃기네", "likeCount": 50, "sentiment": "POSITIVE", "topic": "막내 귀여움", "x": 116.86790466308594, "y": 107.1081771850586, "z": -55.97247314453125, "x2d": 86.35681915283203, "y2d": -4.485711574554443}, {"id": "Ugx5cZO-uF1xJuf21IJ4AaABAg", "text": "아 진짜 막내 너무 귀엽네ㅋㅋㅋ", "likeCount": 49, "sentiment": "POSITIVE", "topic": "막내 귀여움", "x": 145.8500518798828, "y": -76.34214782714844, "z": 25.558481216430664, "x2d": 133.00949096679688, "y2d": 116.60943603515625}, {"id": "UgzHzYVviNTP3jlPMJF4AaABAg", "text": "2:28 페냥이 펌프", "likeCount": 48, "sentiment": "NEUTRAL", "topic": "막내 귀여움", "x": 128.28445434570312, "y": 12.817770957946777, "z": -104.56035614013672, "x2d": 116.82862091064453, "y2d": -27.016944885253906}, {"id": "UgwEnjqLSfANyAVu7C94AaABAg", "text": "4:01 뭔 만담을 하고 있어 오랑페랑 ㅋㅋㅋ", "likeCount": 45, "sentiment": "POSITIVE", "topic": "막내 귀여움", "x": 94.594970703125, "y": -99.35879516601562, "z": -94.69683074951172, "x2d": 152.86370849609375, "y2d": -53.98432922363281}, {"id": "Ugxxvm1lIhgRtbWvPI54AaABAg", "text": "7:22 착장 진짜 잘어울림", "likeCount": 45, "sentiment": "POSITIVE", "topic": "막내 귀여움", "x": 88.97193908691406, "y": 48.7447624206543, "z": -87.96977233886719, "x2d": 59.42269515991211, "y2d": -20.708358764648438}, {"id": "UgxnR3UQRpzuinJySF94AaABAg", "text": "4:15  천장ㅜㅜㅠ귀여워ㅡㅜㅜ", "likeCount": 45, "sentiment": "POSITIVE", "topic": "막내 귀여움", "x": 161.88526916503906, "y": -43.214752197265625, "z": -93.11776733398438, "x2d": 139.3435821533203, "y2d": -36.74294662475586}, {"id": "UgweT1oIFhPYtNQR87B4AaABAg", "text": "아이씨 막내 졸귀력 미쳤나 ㅋㅋㅋㄱㅋㅋ", "likeCount": 44, "sentiment": "POSITIVE", "topic": "막내 귀여움", "x": 102.51829528808594, "y": -79.07708740234375, "z": 25.39971351623535, "x2d": 115.2488021850586, "y2d": 104.26589965820312}, {"id": "UgwSj8ZAWxEWiQ5Fcbd4AaABAg", "text": "6:19 ㅋㅋㅋㅋ여기서부터 개웃기네ㅋㅋㅋ수환이 ㅋㅋㅋ 어켘ㅋㅋㅋㅋ", "likeCount": 41, "sentiment": "POSITIVE", "topic": "막내 귀여움", "x": 109.85763549804688, "y": 85.34427642822266, "z": -19.9337158203125, "x2d": 67.45532989501953, "y2d": 23.21784210205078}, {"id": "UgxunD7KgIvZaUnJunN4AaABAg.AYYL82QtxYfAYYVatSJ0p3", "text": "ㅇㅈㅇㅈ 목각인형 마냥 뚝딱거리는 거 졸귀", "likeCount": 41, "sentiment": "POSITIVE", "topic": "막내 귀여움", "x": 81.70932006835938, "y": -47.33134078979492, "z": 11.8109712600708, "x2d": 89.85891723632812, "y2d": 81.43272399902344}, {"id": "UgxT_vbYYBrCuOi9gyt4AaABAg", "text": "보는 내내 광대 찢어지는줄 ㅎ", "likeCount": 41, "sentiment": "POSITIVE", "topic": "막내 귀여움", "x": 66.88095092773438, "y": -76.80216979980469, "z": 5.890178680419922, "x2d": 65.52050018310547, "y2d": 78.57128143310547}, {"id": "Ugx_wwy1sjBceaYQ6VN4AaABAg", "text": "아니 이 영상 김솬 막내력 뭐임?\n걍 서 있는 거 얼딩인디. (̨̡՞ᓀᴥᖜ՞)̧̢\n미춰버리겟다.", "likeCount": 40, "sentiment": "POSITIVE", "topic": "막내 귀여움", "x": 32.22075653076172, "y": -55.503273010253906, "z": 78.4330825805664, "x2d": -24.50380516052246, "y2d": 94.0682373046875}, {"id": "UgzLpgCGRLV7PTE093Z4AaABAg", "text": "오너 나올 때마나 도넛 먹고 있는 거 웃기네ㅋㅋㅋㅋ 케리아는 요즘 웃음이 많아졌네 ㅋㅋㅋㅋ", "likeCount": 35, "sentiment": "POSITIVE", "topic": "막내 귀여움", "x": -83.38798522949219, "y": 109.24822235107422, "z": -220.0, "x2d": 86.40748596191406, "y2d": -195.5426788330078}, {"id": "Ugx_kVj-oQCUFhtd2wB4AaABAg", "text": "1:06 오너 페이커 주먹으로 만들어진 하트 모양 모자이크 된거 웃기네ㅋㅋㅋㅋㅋ", "likeCount": 28, "sentiment": "POSITIVE", "topic": "팀 분위기와 케미", "x": 3.5218424797058105, "y": 152.0723114013672, "z": -44.83655548095703, "x2d": 6.81525993347168, "y2d": -86.99932098388672}, {"id": "UgwFdwLqnU4N6uep6H54AaABAg", "text": "페이즈 선수랑 화목한거 너무좋다", "likeCount": 27, "sentiment": "POSITIVE", "topic": "팀 분위기와 케미", "x": -33.62714385986328, "y": 191.9424285888672, "z": -12.806256294250488, "x2d": -40.599853515625, "y2d": -103.8308334350586}, {"id": "Ugz12RZCsqQUg8Nk3254AaABAg", "text": "도오페페케 화이팅.... T1 화이팅....", "likeCount": 25, "sentiment": "POSITIVE", "topic": "팀 분위기와 케미", "x": -149.92440795898438, "y": -59.03024673461914, "z": 75.17302703857422, "x2d": -164.4194793701172, "y2d": 6.728303909301758}, {"id": "Ugy1NZdyBmejxLBD9Vl4AaABAg", "text": "수환이 진짜 귀엽네 아", "likeCount": 24, "sentiment": "POSITIVE", "topic": "팀 분위기와 케미", "x": 118.8182601928711, "y": 1.9291082620620728, "z": 41.694454193115234, "x2d": 85.49884796142578, "y2d": 128.67483520507812}, {"id": "UgxtOon8UOeB1xfTsbl4AaABAg", "text": "컨텐츠 축복이 끝이 없네 행복하다", "likeCount": 19, "sentiment": "POSITIVE", "topic": "팀 분위기와 케미", "x": -31.633649826049805, "y": 49.734153747558594, "z": 134.25482177734375, "x2d": -55.7722053527832, "y2d": 49.57047653198242}, {"id": "Ugy0nNZg2-ac8s0UIgl4AaABAg", "text": "아 페이즈 미치겠다 파이팅 포즈 나올때마다 오케마냥 속절없이 무너짐", "likeCount": 17, "sentiment": "NEGATIVE", "topic": "팀 분위기와 케미", "x": -18.905546188354492, "y": 205.2643585205078, "z": -30.540372848510742, "x2d": -30.238454818725586, "y2d": -108.3659439086914}, {"id": "UgwiYqxTr2ACDWkIX314AaABAg", "text": "6:43 after a year..Doran looks more relaxed with the shoots and ads,", "likeCount": 16, "sentiment": "NEUTRAL", "topic": "팀 분위기와 케미", "x": -99.32745361328125, "y": -43.222320556640625, "z": -52.34733963012695, "x2d": -107.4487533569336, "y2d": -87.45008087158203}, {"id": "UgzpvQ8NKSTH2ffF2XZ4AaABAg", "text": "케리아 숨넘어간닼ㅋㅋㅋㅋㅋㅋㅋㅋㅋ", "likeCount": 11, "sentiment": "POSITIVE", "topic": "팀 분위기와 케미", "x": -125.51637268066406, "y": 137.54176330566406, "z": -216.55162048339844, "x2d": 63.51911163330078, "y2d": -212.47032165527344}, {"id": "Ugy5uX6gVchQfV6zJ8R4AaABAg", "text": "일부러 저렇게 모은 것도 아닌데 어쩌다가 팀 전체가 훈훈한 비주얼이 된거냐", "likeCount": 11, "sentiment": "POSITIVE", "topic": "팀 분위기와 케미", "x": -18.523130416870117, "y": 43.0052490234375, "z": 8.73050594329834, "x2d": -1.7409493923187256, "y2d": 33.47895812988281}, {"id": "UgxbBOA3VJN99jG5rk14AaABAg", "text": "므시 가보자", "likeCount": 10, "sentiment": "NEUTRAL", "topic": "팀 분위기와 케미", "x": 120.24302673339844, "y": -100.8347396850586, "z": -34.57606506347656, "x2d": 144.0379638671875, "y2d": 46.81553649902344}, {"id": "Ugzl_5qQy_TYRj3bXs94AaABAg", "text": "도련님 왜 이렇게 사랑스러움... 미드정글 케미 넘 좋음... 도란 청바지 착장 찰떡임... 케리아 미모 미쳤음...", "likeCount": 7, "sentiment": "POSITIVE", "topic": "팀 분위기와 케미", "x": -90.29601287841797, "y": 90.94759368896484, "z": -204.32557678222656, "x2d": 81.39777374267578, "y2d": -165.5799560546875}, {"id": "UgwSXmbi3qtvCBUjqZh4AaABAg", "text": "합성이미지에서는 무섭게 자연스러워지는 상혁씨 ㄷㄷㄷ", "likeCount": 4, "sentiment": "NEUTRAL", "topic": "팀 분위기와 케미", "x": 65.9114990234375, "y": 44.20786666870117, "z": 98.40151977539062, "x2d": 27.75727081298828, "y2d": 115.32131958007812}, {"id": "UgzUT9KZgWuT4i9iad14AaABAg", "text": "케리아 진짜 존잘이네", "likeCount": 3, "sentiment": "POSITIVE", "topic": "팀 분위기와 케미", "x": -118.55470275878906, "y": 108.14314270019531, "z": -198.7593231201172, "x2d": 53.62883758544922, "y2d": -217.74005126953125}, {"id": "UgxkV1TC7TFFHRFu8Vd4AaABAg", "text": "5:50 ✌️ 케리아\n6:10 💪 도란", "likeCount": 3, "sentiment": "POSITIVE", "topic": "팀 분위기와 케미", "x": -89.97235870361328, "y": 65.03292083740234, "z": -175.53797912597656, "x2d": 65.4568099975586, "y2d": -179.3472137451172}, {"id": "Ugz_2FS16-tAw21maaN4AaABAg.AYYOmDN_Go7AYZXaNR4bIx", "text": "페이즈 덕에 분위기 엄청 좋네요", "likeCount": 3, "sentiment": "POSITIVE", "topic": "팀 분위기와 케미", "x": -25.011972427368164, "y": 209.8686065673828, "z": -8.048776626586914, "x2d": -35.39281463623047, "y2d": -93.59146881103516}, {"id": "UgzGRpNRJn8IVO--Ild4AaABAg", "text": "쿨톤 상혁", "likeCount": 3, "sentiment": "NEUTRAL", "topic": "팀 분위기와 케미", "x": 20.81963348388672, "y": 137.3993377685547, "z": 94.93445587158203, "x2d": -0.11342867463827133, "y2d": 74.52669525146484}, {"id": "UgwqQzvvBzaLM--dErx4AaABAg", "text": "도오페페케 모두 넘 잘생겼다 ❤❤❤❤❤❤", "likeCount": 2, "sentiment": "POSITIVE", "topic": "팀 분위기와 케미", "x": -152.45565795898438, "y": -20.980161666870117, "z": 61.97213363647461, "x2d": -129.36280822753906, "y2d": -15.377403259277344}, {"id": "Ugzt0frM_nZSNXxNxeJ4AaABAg", "text": "2:28 란이는 누구 자켓을 입은 걸까..?\n의자에 걸려있는게 란이 자켓인데", "likeCount": 2, "sentiment": "NEUTRAL", "topic": "팀 분위기와 케미", "x": 68.54008483886719, "y": 20.676071166992188, "z": -103.1156997680664, "x2d": 69.59077453613281, "y2d": -53.18806838989258}, {"id": "UgyY2h3pWUzbgqU1uop4AaABAg", "text": "2", "likeCount": 2, "sentiment": "NEUTRAL", "topic": "팀 분위기와 케미", "x": 22.38623809814453, "y": -156.24087524414062, "z": -89.45901489257812, "x2d": 169.5146026611328, "y2d": -20.30365753173828}, {"id": "UgytjGNsxqIV-UpWbdh4AaABAg", "text": "삼성 모니터와 티원 콜라보 제품도 나올만 한데...", "likeCount": 1, "sentiment": "NEUTRAL", "topic": "팀 분위기와 케미", "x": 23.947114944458008, "y": -28.53981590270996, "z": 148.30963134765625, "x2d": -23.359115600585938, "y2d": 166.05032348632812}, {"id": "UgxE_7OtYP-nMxzcnPp4AaABAg", "text": "아 천장에 손박은 대장님 표정 개구ㅣ엽네 ㅋ ㅋ 큐ㅠ", "likeCount": 1, "sentiment": "POSITIVE", "topic": "팀 분위기와 케미", "x": 32.8917350769043, "y": -72.24422454833984, "z": -125.88236236572266, "x2d": 98.79679870605469, "y2d": -98.51980590820312}, {"id": "Ugyo6XyHTgu0k9FLwll4AaABAg", "text": "다들 미모가 레벨업했네 ෆ˙ᵕ˙ෆ", "likeCount": 1, "sentiment": "POSITIVE", "topic": "팀 분위기와 케미", "x": 92.65449523925781, "y": -96.82923889160156, "z": -65.8060531616211, "x2d": 134.88162231445312, "y2d": -22.00337791442871}, {"id": "UgzxTXa4nzgMykVPIad4AaABAg", "text": "2:29 Doran's JK is over the chair. Doran is wearing Oner's JK 😳", "likeCount": 1, "sentiment": "NEUTRAL", "topic": "팀 분위기와 케미", "x": -88.41546630859375, "y": -76.99075317382812, "z": -73.58314514160156, "x2d": -101.8919906616211, "y2d": -100.58867645263672}, {"id": "UgwUf_fmKfrvWpkfXzJ4AaABAg", "text": "문도 왜케 피곤해보여 ㄷㄷ", "likeCount": 1, "sentiment": "NEGATIVE", "topic": "팀 분위기와 케미", "x": 7.360289096832275, "y": 100.13898468017578, "z": 25.695068359375, "x2d": -8.84661865234375, "y2d": 24.734094619750977}, {"id": "Ugyehtzy32EcBLa8rHt4AaABAg", "text": "굼시없으니까 분위기삭막하긴하네😅", "likeCount": 0, "sentiment": "NEGATIVE", "topic": "팀 분위기와 케미", "x": 81.9789047241211, "y": -86.91605377197266, "z": 75.21328735351562, "x2d": 113.29669189453125, "y2d": 132.77236938476562}, {"id": "Ugyehtzy32EcBLa8rHt4AaABAg.AYYX8sWpIWgAYZV5XgVDAm", "text": "좀 꺼져라 질척거리지 말고", "likeCount": 0, "sentiment": "NEGATIVE", "topic": "팀 분위기와 케미", "x": 35.2673225402832, "y": 15.922713279724121, "z": 21.774580001831055, "x2d": 51.10744857788086, "y2d": 70.68095397949219}, {"id": "Ugwvzqk5x0f474uCI854AaABAg", "text": "셔츠혁 왜케 잘생겼냐", "likeCount": 0, "sentiment": "POSITIVE", "topic": "팀 분위기와 케미", "x": -8.895155906677246, "y": 144.3937225341797, "z": 78.84447479248047, "x2d": -27.972610473632812, "y2d": 7.130507946014404}, {"id": "Ugw7IuzZQ9kTF2gFxRt4AaABAg", "text": "삼성 오디셰이ㅋㅋㅋㅋㅋㅋㅋㅋㅋㅋㅋㅋㅋㅋㅋㅋㅋㅋㅋㅋㅋㅋㅋㅋㅋㅋㅋㅋㅋㅋㅋㅋㅋㅋ", "likeCount": 0, "sentiment": "POSITIVE", "topic": "팀 분위기와 케미", "x": 42.48630905151367, "y": -43.33882141113281, "z": 161.21739196777344, "x2d": -11.493642807006836, "y2d": 195.3036651611328}, {"id": "UgygTA1lLMkLcoi_Jfx4AaABAg", "text": "6:02 촬영에 익숙한 오너 페이커 / 어색한 페이즈 도란 구도 너무 웃기다ㅋㅋㅋㅋㅋ", "likeCount": 418, "sentiment": "POSITIVE", "topic": "촬영 장면의 귀여움", "x": -8.095044136047363, "y": 131.14291381835938, "z": -27.916446685791016, "x2d": -18.252399444580078, "y2d": -59.143707275390625}, {"id": "Ugylm6JBmh-fSwOCehJ4AaABAg", "text": "3:30 수환이 부를때마다 대긴장한상태로 네?! 해주는거 ㄱㅇㅇ ㅠㅋㅋㅋ", "likeCount": 331, "sentiment": "POSITIVE", "topic": "촬영 장면의 귀여움", "x": 56.62766647338867, "y": -52.94289016723633, "z": -91.51710510253906, "x2d": 57.01926040649414, "y2d": 15.2017822265625}, {"id": "UgzxQqC-yJCkQn31j214AaABAg", "text": "뭐야 영상 업로드가 왤케 빨라졌지..?", "likeCount": 163, "sentiment": "NEUTRAL", "topic": "촬영 장면의 귀여움", "x": -14.599076271057129, "y": -10.588788986206055, "z": 84.85281372070312, "x2d": -60.39461898803711, "y2d": 26.014001846313477}, {"id": "Ugzwbd2FpjF1HGXwhzV4AaABAg", "text": "6:36 케리아 이렇게 웃는거 처음 보는거 같은데 ㄷㄷㄷㄷ", "likeCount": 116, "sentiment": "POSITIVE", "topic": "촬영 장면의 귀여움", "x": -96.00765991210938, "y": 84.77919006347656, "z": -186.30088806152344, "x2d": 58.704185485839844, "y2d": -192.44369506835938}, {"id": "UgxCw4FWyGtERh0TmNR4AaABAg", "text": "6:13 Doran so cute hehehehehe", "likeCount": 73, "sentiment": "POSITIVE", "topic": "촬영 장면의 귀여움", "x": -98.7394027709961, "y": -97.08853149414062, "z": -66.18258666992188, "x2d": -121.4410171508789, "y2d": -102.18470764160156}, {"id": "UgxuushpZ80BPNnIbRl4AaABAg", "text": "6:17 엉거주춤 페이즈 너무 웃기다 ㅋㅋㄱㅋㄱㅋㄱㅋㄱㅋ 아 계속 돌려봤네", "likeCount": 55, "sentiment": "POSITIVE", "topic": "촬영 장면의 귀여움", "x": 20.59342384338379, "y": 149.6786651611328, "z": -39.2575798034668, "x2d": -1.2909839153289795, "y2d": -72.10348510742188}, {"id": "UgxOY42CNKsMzXcqG5x4AaABAg", "text": "5:52 티원봇규 세젤귀", "likeCount": 48, "sentiment": "POSITIVE", "topic": "촬영 장면의 귀여움", "x": 133.73532104492188, "y": 54.89177322387695, "z": -70.16146850585938, "x2d": 91.46699523925781, "y2d": -21.237340927124023}, {"id": "UgxN8ZJhEAK8p7eR0Bt4AaABAg", "text": "5:50 귀여워ㅠㅠㅠ", "likeCount": 41, "sentiment": "POSITIVE", "topic": "촬영 장면의 귀여움", "x": 144.18373107910156, "y": 22.114606857299805, "z": -64.6163330078125, "x2d": 112.89701080322266, "y2d": -9.908866882324219}, {"id": "UgxuSkhbH7-wXlYppvR4AaABAg", "text": "란이랑 페이커 둘 다 키도 커서 뭘 입어도 예쁘고 잘 어울림", "likeCount": 32, "sentiment": "POSITIVE", "topic": "촬영 장면의 귀여움", "x": -19.317363739013672, "y": 168.18678283691406, "z": 3.5097081661224365, "x2d": -38.59899139404297, "y2d": -61.818199157714844}, {"id": "Ugz7B1tXPkmqSRNBJ7R4AaABAg", "text": "도련님 개귀엽네 ㅋㅋㅋㅋㅋㅋㅋㅋㅋㅋㅋㅋㅋㅋㅋ", "likeCount": 25, "sentiment": "POSITIVE", "topic": "촬영 장면의 귀여움", "x": 26.430578231811523, "y": -76.70812225341797, "z": -117.10670471191406, "x2d": 84.81815338134766, "y2d": -102.5300064086914}, {"id": "UgzJ4E1Kz4U5xNErlhl4AaABAg", "text": "막냉이 너무 사랑스럽다😂", "likeCount": 20, "sentiment": "POSITIVE", "topic": "촬영 장면의 귀여움", "x": 110.22883605957031, "y": -110.57411193847656, "z": 52.68852996826172, "x2d": 122.3856201171875, "y2d": 126.34690856933594}, {"id": "Ugw8ATraB1XwJP0t9kB4AaABAg", "text": "수환이땜에 민석이 현준이 숨넘어가넼 ㅋㅋㅋㅋㅋㅋㅋㅋㅋ", "likeCount": 12, "sentiment": "POSITIVE", "topic": "촬영 장면의 귀여움", "x": 75.31230926513672, "y": 98.40904235839844, "z": 69.0839614868164, "x2d": 30.645383834838867, "y2d": 98.64790344238281}, {"id": "Ugwi0qDHKK1msa5tjH54AaABAg", "text": "4:15 아무일 없는 척하는 대장님\n5:49 개존귀 케리아\n6:33 도련님ㅋㅋ큐ㅠㅠㅠㅠㅠ\n7:32 빠이야 ㅋㅌㅋㅋㅋㅋㅋ\n7:46 그윽란 & 오시렁오시렁", "likeCount": 12, "sentiment": "POSITIVE", "topic": "촬영 장면의 귀여움", "x": 84.50174713134766, "y": -67.71198272705078, "z": -133.02357482910156, "x2d": 111.41246795654297, "y2d": -121.2022476196289}, {"id": "UgzCSg8DA7a5TevTKCN4AaABAg", "text": "란이 사진 잘 나왔던데 영상도 예쁘게 나왔구나", "likeCount": 11, "sentiment": "POSITIVE", "topic": "촬영 장면의 귀여움", "x": -20.77578353881836, "y": 29.65645980834961, "z": 79.433837890625, "x2d": -62.48027038574219, "y2d": 15.008369445800781}, {"id": "Ugw3cvLhN1OPEar3AWt4AaABAg", "text": "솬이 웃음 지어보는 로봇같네요 ㅋㅋㅋㅋ란도가 많이 없는 거 같아 아쉽지만 다음에는 촬영에 많이 잡혀보자!! 솬이, 민석이, 현준이들, 우리 혁이 다들 msi 화이팅!!", "likeCount": 9, "sentiment": "POSITIVE", "topic": "촬영 장면의 귀여움", "x": 24.432514190673828, "y": -65.76748657226562, "z": 116.77398681640625, "x2d": -18.247840881347656, "y2d": 140.92225646972656}, {"id": "Ugw5Zx-5gk_2yjVfK8R4AaABAg", "text": "저는 수환이 진짜 스타성이 있는 것 같아요. 잘하는 것뿐만 아니라,가만히 있어도 '다음에는 또 뭘 할까?' 하고 괜히 궁금하게 만드는 사람이랄까요. 게다가 성격도 정말 흥미롭고요.", "likeCount": 9, "sentiment": "POSITIVE", "topic": "촬영 장면의 귀여움", "x": 90.49271392822266, "y": 41.05027770996094, "z": 79.25568389892578, "x2d": 57.401145935058594, "y2d": 118.59123229980469}, {"id": "UgxxJMY_O3fdw4aHB0R4AaABAg", "text": "0:33 미모봐라", "likeCount": 9, "sentiment": "POSITIVE", "topic": "촬영 장면의 귀여움", "x": 103.4581069946289, "y": -129.06826782226562, "z": -73.59093475341797, "x2d": 148.89634704589844, "y2d": 4.7205586433410645}, {"id": "Ugx-sxZXHn3XTe-7sQt4AaABAg", "text": "3:43 너무 귀여워 진짜 주먹밥쿵야 같아\n6:05 너무 귀여워 너무귀여워 ㅠㅠ", "likeCount": 8, "sentiment": "POSITIVE", "topic": "촬영 장면의 귀여움", "x": 153.32928466796875, "y": -6.933509349822998, "z": -25.818017959594727, "x2d": 109.40156555175781, "y2d": 46.86930465698242}, {"id": "UgxQnCcpPSJM3GUzTu14AaABAg", "text": "수환이 되게 정석미남은 아닌데 진짜 개매력있는 얼굴임… 아 귀엽다", "likeCount": 7, "sentiment": "POSITIVE", "topic": "촬영 장면의 귀여움", "x": 112.69729614257812, "y": 5.363412380218506, "z": 76.109619140625, "x2d": 67.61536407470703, "y2d": 141.40667724609375}, {"id": "Ugz38AXDlDNyxyfk3nZ4AaABAg", "text": "6:09 너무 귀엽다", "likeCount": 7, "sentiment": "POSITIVE", "topic": "촬영 장면의 귀여움", "x": 148.8860626220703, "y": -18.355100631713867, "z": -20.80656623840332, "x2d": 115.12614440917969, "y2d": 36.63312911987305}, {"id": "Ugykxzs2SsPxkbnjEox4AaABAg", "text": "그 사진들이 합성이 아니엇다니 ㅋㅋㅋㅋㅋㅋ", "likeCount": 7, "sentiment": "POSITIVE", "topic": "촬영 장면의 귀여움", "x": 66.17853546142578, "y": 11.341036796569824, "z": 112.14783477783203, "x2d": 13.448500633239746, "y2d": 134.65728759765625}, {"id": "UgxO0_AzT0icOMCMxHJ4AaABAg", "text": "캬 삼성광고라니 ㅋㅋ", "likeCount": 6, "sentiment": "POSITIVE", "topic": "촬영 장면의 귀여움", "x": 34.220741271972656, "y": -69.9830551147461, "z": 175.29420471191406, "x2d": -24.310266494750977, "y2d": 192.8793487548828}, {"id": "UgyxmwQr4geDW7xfTDV4AaABAg", "text": "Family is so cute OMG 😭", "likeCount": 5, "sentiment": "POSITIVE", "topic": "촬영 장면의 귀여움", "x": -153.8665008544922, "y": -100.36012268066406, "z": -18.809919357299805, "x2d": -153.82415771484375, "y2d": -97.98430633544922}, {"id": "UgxntCqXb7tHCgWM7Yp4AaABAg", "text": "역시 대기업광고 비하인드는 빠르군", "likeCount": 5, "sentiment": "NEUTRAL", "topic": "촬영 장면의 귀여움", "x": -38.25686264038086, "y": -11.990229606628418, "z": 158.41526794433594, "x2d": -84.92816925048828, "y2d": 112.09000396728516}, {"id": "UgxGcHxTFfV83q4KShF4AaABAg", "text": "페이즈 저렇게 뚝딱거리는거 너무 이해됨...평소에 자연스럽게 하던 동작도 갑자기 누가 말로 설명해주면서 해보라고 하면 팔다리가 다 따로 놀면서 코딩 꼬임...ㅋㅋㅋ", "likeCount": 4, "sentiment": "POSITIVE", "topic": "촬영 장면의 귀여움", "x": -3.928692102432251, "y": 173.68173217773438, "z": -20.188983917236328, "x2d": -20.932695388793945, "y2d": -75.02685546875}, {"id": "UgwAKJBVgA9k-mtBsDd4AaABAg", "text": "They are so cute!!!!! Peyz's still awkward.. but it's also his charm🥰🥰🥰🥰", "likeCount": 4, "sentiment": "POSITIVE", "topic": "촬영 장면의 귀여움", "x": -181.91758728027344, "y": -116.64331817626953, "z": -36.83694076538086, "x2d": -170.25343322753906, "y2d": -126.72533416748047}, {"id": "UgyUaU5ztMeLynRVpZ94AaABAg", "text": "peyz kenapa gemes banget nak 😂", "likeCount": 4, "sentiment": "POSITIVE", "topic": "촬영 장면의 귀여움", "x": -190.18348693847656, "y": -107.16266632080078, "z": -42.08494186401367, "x2d": -177.35806274414062, "y2d": -135.8105926513672}, {"id": "Ugzk5VuWQHto6tjjrkZ4AaABAg", "text": "대.삼.성.오디세이 분들,, 당연히 포카도 낋여오셨겠쥬..?!!\n착장 넘넘 이쁩니다!!!!!!! \n저 삼성티비, 삼성폰, 삼성놑북, 삼성모니터, 삼성세탁기 &건조기 사용중입니다!!!!!", "likeCount": 4, "sentiment": "POSITIVE", "topic": "촬영 장면의 귀여움", "x": 37.49644088745117, "y": -75.51362609863281, "z": 186.27340698242188, "x2d": -30.233707427978516, "y2d": 203.751708984375}, {"id": "Ugx2ja2OY4r97esMMQh4AaABAg", "text": "도란 인터뷰가 없네 ㅜㅜ", "likeCount": 3, "sentiment": "NEGATIVE", "topic": "촬영 장면의 귀여움", "x": -21.335376739501953, "y": 4.056114196777344, "z": 111.33715057373047, "x2d": -66.67241668701172, "y2d": 55.23583221435547}, {"id": "Ugzan5cV5I238hvc78t4AaABAg", "text": "2:30 도란의 재킷은 의자 위에 있는데, 그럼 그가 입고 있는 재킷은 누구의 것인가요? 🤔🤭", "likeCount": 3, "sentiment": "NEUTRAL", "topic": "촬영 장면의 귀여움", "x": 45.48991394042969, "y": 7.347930908203125, "z": -101.94813537597656, "x2d": 50.59910202026367, "y2d": -76.75789642333984}, {"id": "UgwphTJcQfVrF0qBf3d4AaABAg", "text": "7:04 우리혁 왤케 잘생김? 가디건혁 미쳤다", "likeCount": 278, "sentiment": "POSITIVE", "topic": "선수들의 외모", "x": -0.40914782881736755, "y": 127.1583251953125, "z": 75.10102844238281, "x2d": -12.280937194824219, "y2d": 9.949060440063477}, {"id": "UgwvD7Tnd0xF70Jcwip4AaABAg", "text": "5:16 셔츠혁 진짜 개잘생겼네", "likeCount": 176, "sentiment": "POSITIVE", "topic": "선수들의 외모", "x": 33.14949417114258, "y": 120.24169921875, "z": 55.81501388549805, "x2d": 1.937211275100708, "y2d": 8.426350593566895}, {"id": "UgwsG9eZLurXdpVU25x4AaABAg", "text": "5:48 하늘색 니트가디건 너무 잘어울린다 대~상혁", "likeCount": 69, "sentiment": "POSITIVE", "topic": "선수들의 외모", "x": 125.53614807128906, "y": 85.32505798339844, "z": -79.16925811767578, "x2d": 35.474365234375, "y2d": -23.552263259887695}, {"id": "UgxunD7KgIvZaUnJunN4AaABAg.AYYL82QtxYfAYYYS2c5AFw", "text": "오너 케리아 정신을 못차리네 ㅋㅋㅋㅋㅋㅋ", "likeCount": 30, "sentiment": "POSITIVE", "topic": "선수들의 외모", "x": -116.2854232788086, "y": 130.14321899414062, "z": -206.84938049316406, "x2d": 69.45458221435547, "y2d": -202.45697021484375}, {"id": "UgxzFRb-drXn3e9Zyb54AaABAg", "text": "다섯명 다 외모도 훈훈하네요.", "likeCount": 29, "sentiment": "POSITIVE", "topic": "선수들의 외모", "x": 5.772192478179932, "y": 45.16127395629883, "z": -12.623395919799805, "x2d": 27.091012954711914, "y2d": 43.194881439208984}, {"id": "UgxeDMHRYyoFlqOqlzx4AaABAg", "text": "수환이 개웃기내", "likeCount": 22, "sentiment": "POSITIVE", "topic": "선수들의 외모", "x": 91.38677215576172, "y": 68.26024627685547, "z": 41.71754837036133, "x2d": 84.48066711425781, "y2d": 91.82624816894531}, {"id": "UgwNhUq33BC97zLE5CF4AaABAg", "text": "솬이 너무 기엽다 ㅋㅋㅋㅋㅋㅋㅋㅋㅋ", "likeCount": 21, "sentiment": "POSITIVE", "topic": "선수들의 외모", "x": 58.1781120300293, "y": -69.39247131347656, "z": 112.84368896484375, "x2d": 16.9773006439209, "y2d": 170.73793029785156}, {"id": "Ugyat4Pnpw8PthVNved4AaABAg", "text": "와 페이커 왜케 잘생김", "likeCount": 11, "sentiment": "POSITIVE", "topic": "선수들의 외모", "x": -22.773273468017578, "y": 197.46388244628906, "z": 29.76554298400879, "x2d": -35.24519729614258, "y2d": -32.82363510131836}, {"id": "UgxNMymUh0DqE52Y74x4AaABAg", "text": "와 케리아 겁나 잘생김 귀여운건 덤이고 캬", "likeCount": 6, "sentiment": "POSITIVE", "topic": "선수들의 외모", "x": -126.46765899658203, "y": 156.4603729248047, "z": -205.51162719726562, "x2d": 43.672210693359375, "y2d": -223.41552734375}, {"id": "Ugylm6JBmh-fSwOCehJ4AaABAg.AYYKMmuNgipAYYM-M5arjT", "text": "Who is Suhwan?", "likeCount": 5, "sentiment": "NEUTRAL", "topic": "선수들의 외모", "x": 59.838417053222656, "y": 154.6325225830078, "z": 74.10074615478516, "x2d": 11.428197860717773, "y2d": 84.80583953857422}, {"id": "UgxEVFiSpTTt4y0gfW94AaABAg", "text": "다행이네 대수환 티밥 잘 맞나보다 살오른것 보소", "likeCount": 4, "sentiment": "POSITIVE", "topic": "선수들의 외모", "x": -5.17731237411499, "y": 208.4287109375, "z": 31.142852783203125, "x2d": -46.25798416137695, "y2d": -49.96772384643555}, {"id": "UgyVUJKmygQmQ5QCjzt4AaABAg", "text": "탑정글 한국 선수 아무나 골라잡아도 티원 그슬할거같은데..", "likeCount": 3, "sentiment": "NEUTRAL", "topic": "선수들의 외모", "x": -86.82176971435547, "y": 57.09543991088867, "z": 94.30158233642578, "x2d": -117.18091583251953, "y2d": 63.256370544433594}, {"id": "UgxwB974JG5OFP2znzR4AaABAg", "text": "케리아 존나 잘생겼네 ; 뭐임?", "likeCount": 3, "sentiment": "POSITIVE", "topic": "선수들의 외모", "x": -120.5741958618164, "y": 131.81924438476562, "z": -183.17495727539062, "x2d": 40.143951416015625, "y2d": -212.40882873535156}, {"id": "UgyEGCPnl9m7HEsruHp4AaABAg", "text": "티원영상 볼때마다 선수들\n얼굴이 훤칠해지네 ㅋㅋㅋㅋㅋㅋㅋㅋㅋ\n오늘 경기도 화이팅이야🎉", "likeCount": 1, "sentiment": "POSITIVE", "topic": "선수들의 외모", "x": -94.27566528320312, "y": 23.445505142211914, "z": 82.42168426513672, "x2d": -132.70755004882812, "y2d": 37.509193420410156}, {"id": "UgwsM7THDKDV78PQrkp4AaABAg", "text": "ㅋㅋㅋㅋㅋㅋ 우리 페이커 선수는 왜 이렇게 진지한 자리에서 더 장난꾸러기가 되는 거죠?", "likeCount": 1, "sentiment": "POSITIVE", "topic": "선수들의 외모", "x": -41.90835952758789, "y": 220.0, "z": -4.680850028991699, "x2d": -50.378143310546875, "y2d": -87.95280456542969}, {"id": "Ugx70vEZABalM5i6K_B4AaABAg", "text": "이상혁선수👍👍👍👍👍👍", "likeCount": 0, "sentiment": "POSITIVE", "topic": "선수들의 외모", "x": 39.23178482055664, "y": 173.90487670898438, "z": 96.72852325439453, "x2d": -21.448633193969727, "y2d": 80.53761291503906}, {"id": "Ugy7g6xghXjLSfz_gI54AaABAg", "text": "10등", "likeCount": 0, "sentiment": "NEUTRAL", "topic": "선수들의 외모", "x": 23.240015029907227, "y": -138.26170349121094, "z": -84.6748275756836, "x2d": 174.52830505371094, "y2d": -5.2337965965271}, {"id": "UgzpdDRsxODmyI8JS1x4AaABAg", "text": "조회수 4", "likeCount": 0, "sentiment": "NEUTRAL", "topic": "선수들의 외모", "x": 53.70315933227539, "y": -139.19627380371094, "z": -94.2743148803711, "x2d": 162.34579467773438, "y2d": -34.247127532958984}, {"id": "Ugxy4O5RYKO43V4Wj8l4AaABAg", "text": "사랑해요.. 삼성 오딧세이..\n\n", "likeCount": 187, "sentiment": "POSITIVE", "topic": "팬들의 응원과 기대", "x": 19.756200790405273, "y": -99.24486541748047, "z": 200.16729736328125, "x2d": -64.66529846191406, "y2d": 208.1194610595703}, {"id": "Ugy3l2nboc9daB9ziAN4AaABAg", "text": "06:14  사진 공개되고 팬들이 가장 궁금해하던(웃겨하던) 그 장면", "likeCount": 34, "sentiment": "NEUTRAL", "topic": "팬들의 응원과 기대", "x": -49.426143646240234, "y": 69.57137298583984, "z": -15.750484466552734, "x2d": -44.38943862915039, "y2d": -39.09584045410156}, {"id": "Ugymib8qOfFalJCdzP14AaABAg", "text": "진짜 새삼 느끼는거지만 티원 선수들 겁나 바쁘긴하다 ㄷㄷ", "likeCount": 22, "sentiment": "NEUTRAL", "topic": "팬들의 응원과 기대", "x": -101.22728729248047, "y": 34.60459899902344, "z": 86.93925476074219, "x2d": -148.264892578125, "y2d": 48.67045974731445}, {"id": "UgxSpjY54tkwfzBc-Rp4AaABAg", "text": "6:33 Peyz is so cuteeeeeee!!! <3 T1, let's gooooooooo", "likeCount": 21, "sentiment": "POSITIVE", "topic": "팬들의 응원과 기대", "x": -205.79661560058594, "y": -143.31602478027344, "z": -21.46717071533203, "x2d": -192.21331787109375, "y2d": -109.25062561035156}, {"id": "Ugz2fdNQN2yjS5KaQu14AaABAg", "text": "도련님 진짜 개웃기다 ㅠㅋㅋㅋㅋㅋㅋㅋㅋㅋㅋㅋㅋㅋㅋㅋㅋㅋㅋㅋㅋㅋ", "likeCount": 13, "sentiment": "POSITIVE", "topic": "팬들의 응원과 기대", "x": -4.217200756072998, "y": -67.18194580078125, "z": -96.2197036743164, "x2d": 55.74024963378906, "y2d": -104.13036346435547}, {"id": "Ugz6fBDAWfcB0d4Ca4R4AaABAg", "text": "티원 내일 경기도 화이팅하자~~!! 줘팸천재 티원", "likeCount": 12, "sentiment": "POSITIVE", "topic": "팬들의 응원과 기대", "x": -133.90859985351562, "y": -36.8181266784668, "z": 116.11276245117188, "x2d": -175.7812042236328, "y2d": 53.64148712158203}, {"id": "Ugylm6JBmh-fSwOCehJ4AaABAg.AYYKMmuNgipAYYMWH3OaH7", "text": "​@Hades-SiredPeyz' real name", "likeCount": 10, "sentiment": "NEUTRAL", "topic": "팬들의 응원과 기대", "x": -214.15042114257812, "y": -153.07952880859375, "z": -37.10441207885742, "x2d": -216.87461853027344, "y2d": -152.87689208984375}, {"id": "UgxUMaVKSLsmhqO8gQ94AaABAg", "text": "ㅋㅋㅋㅋㅋㅋㅋ 내일 화이팅 하자!! 아자아자 도오페페케!!", "likeCount": 10, "sentiment": "POSITIVE", "topic": "팬들의 응원과 기대", "x": -159.54629516601562, "y": -83.07689666748047, "z": 111.07150268554688, "x2d": -191.00379943847656, "y2d": 22.898202896118164}, {"id": "Ugxcouzj4VTqOHskoE14AaABAg", "text": "2:30 도와주시는 표정 맞아요 대장님?ㅋㅋㅋㅋ", "likeCount": 8, "sentiment": "POSITIVE", "topic": "팬들의 응원과 기대", "x": 12.135490417480469, "y": -99.41719818115234, "z": -107.5604476928711, "x2d": 70.62007141113281, "y2d": -92.95977783203125}, {"id": "UgxnT1wRQBzVrzJE8xJ4AaABAg", "text": "2:20 HOLY Oner 💪", "likeCount": 8, "sentiment": "POSITIVE", "topic": "팬들의 응원과 기대", "x": -114.55842590332031, "y": -131.952392578125, "z": -75.00105285644531, "x2d": -138.98287963867188, "y2d": -111.07361602783203}, {"id": "UgyCM-iJa2VOF-4E5oR4AaABAg", "text": "우리혁 셔츠입은거 비하인드 보고싶었는데 압도적 감사", "likeCount": 7, "sentiment": "POSITIVE", "topic": "팬들의 응원과 기대", "x": -40.414527893066406, "y": 65.62056732177734, "z": 120.32524871826172, "x2d": -61.17798614501953, "y2d": 37.67060089111328}, {"id": "UgxgiNLY-mfepiSTSCh4AaABAg", "text": "Msi도 화이팅!!", "likeCount": 5, "sentiment": "POSITIVE", "topic": "팬들의 응원과 기대", "x": -142.322509765625, "y": -90.13793182373047, "z": 128.78468322753906, "x2d": -194.08074951171875, "y2d": 36.08478546142578}, {"id": "UgyqNTaVzey-NzaP2Rh4AaABAg", "text": "오늘도 티손실 해결!!!\n낼 므시 응원해요😊", "likeCount": 5, "sentiment": "POSITIVE", "topic": "팬들의 응원과 기대", "x": -82.84081268310547, "y": -78.42095184326172, "z": 75.49409484863281, "x2d": -133.9195098876953, "y2d": 54.139034271240234}, {"id": "UgzSIlJO4Y48x1TpHJh4AaABAg", "text": "우리티원왓다", "likeCount": 5, "sentiment": "POSITIVE", "topic": "팬들의 응원과 기대", "x": -97.0911865234375, "y": -44.85831832885742, "z": 108.02434539794922, "x2d": -135.03726196289062, "y2d": 89.98234558105469}, {"id": "UgwL1HhownC9iBVTpsB4AaABAg", "text": "peyz😭", "likeCount": 4, "sentiment": "NEGATIVE", "topic": "팬들의 응원과 기대", "x": -223.4326171875, "y": -120.12715148925781, "z": -32.17787551879883, "x2d": -207.10931396484375, "y2d": -146.37289428710938}, {"id": "UgwhqR43PgV0B7nbyRp4AaABAg", "text": "Let's go T1 win ❤", "likeCount": 4, "sentiment": "POSITIVE", "topic": "팬들의 응원과 기대", "x": -184.13380432128906, "y": -103.5816421508789, "z": 35.015968322753906, "x2d": -198.52304077148438, "y2d": -43.18663787841797}, {"id": "UgytaolXcMzl0gHH53V4AaABAg", "text": "HAHAHAHAHAHAH PEYZ me hizo reír Mucho te AMO PEYZ TE AMO T1", "likeCount": 4, "sentiment": "POSITIVE", "topic": "팬들의 응원과 기대", "x": -217.7755889892578, "y": -150.05218505859375, "z": -7.454652309417725, "x2d": -220.0, "y2d": -121.72826385498047}, {"id": "Ugylm6JBmh-fSwOCehJ4AaABAg.AYYKMmuNgipAYYMtJfL8Ow", "text": "@heilo-5269 Thank you Heilo", "likeCount": 4, "sentiment": "NEUTRAL", "topic": "팬들의 응원과 기대", "x": -137.1297149658203, "y": -135.68173217773438, "z": 104.24024963378906, "x2d": -173.9175262451172, "y2d": 0.8416911959648132}, {"id": "UgzhM4AEN99MqWqKWJN4AaABAg", "text": "내일 경기 화이팅!", "likeCount": 3, "sentiment": "POSITIVE", "topic": "팬들의 응원과 기대", "x": -142.900390625, "y": -50.739524841308594, "z": 125.58000183105469, "x2d": -191.4647216796875, "y2d": 51.49455642700195}, {"id": "UgyapM85D1oEpTr0W2h4AaABAg", "text": "Peyz😂😂😂😂😂😂😂👏👏👏👍👍", "likeCount": 3, "sentiment": "POSITIVE", "topic": "팬들의 응원과 기대", "x": -214.62074279785156, "y": -117.56244659423828, "z": -25.593297958374023, "x2d": -201.25318908691406, "y2d": -136.6097412109375}, {"id": "UgxbXd30QKKOsfio_bR4AaABAg", "text": "내일 경기 화이팅!", "likeCount": 3, "sentiment": "POSITIVE", "topic": "팬들의 응원과 기대", "x": -153.56227111816406, "y": -63.31972885131836, "z": 128.5602569580078, "x2d": -188.95082092285156, "y2d": 62.77009201049805}, {"id": "UgzqFJuUIp084Qp_qJV4AaABAg", "text": "❤❤❤", "likeCount": 3, "sentiment": "POSITIVE", "topic": "팬들의 응원과 기대", "x": -188.61911010742188, "y": -110.65734100341797, "z": 11.409211158752441, "x2d": -193.19847106933594, "y2d": -78.51812744140625}, {"id": "Ugy0mYalqMANEfjzIEd4AaABAg", "text": "도명보 나가!! 오영우 나가!! 존나 못하네 투현준 좀 버려라", "likeCount": 2, "sentiment": "NEGATIVE", "topic": "팬들의 응원과 기대", "x": 8.658671379089355, "y": 126.27983093261719, "z": -17.63770866394043, "x2d": -31.06476593017578, "y2d": -43.935585021972656}, {"id": "UgwQ3iv8FU6j7-XY4Nx4AaABAg", "text": "4:33 에이블리는 응답하시오. ㅋ", "likeCount": 1, "sentiment": "POSITIVE", "topic": "팬들의 응원과 기대", "x": 36.323265075683594, "y": -153.85543823242188, "z": -76.34785461425781, "x2d": 124.09988403320312, "y2d": -41.59726333618164}, {"id": "Ugx0N8Ps0cvF59bKrhl4AaABAg", "text": "msi유니폼 언제팔아오? 에이블리에서 기다리고 있습니다!\n내년엔 멤버십 꼭 해야지.... 1년구독할라고 가보니까 하루전에 마감이였더라는", "likeCount": 0, "sentiment": "NEUTRAL", "topic": "팬들의 응원과 기대", "x": -70.48322296142578, "y": -72.2865219116211, "z": 98.6463623046875, "x2d": -111.32250213623047, "y2d": 82.16670989990234}, {"id": "Ugw8zzidDQ-_-VfRh0V4AaABAg", "text": "도오페페케 너무 좋다 진짜 오늘 경기 화이팅입니다", "likeCount": 0, "sentiment": "POSITIVE", "topic": "팬들의 응원과 기대", "x": -167.88241577148438, "y": -58.839393615722656, "z": 99.02098846435547, "x2d": -182.28050231933594, "y2d": 15.229910850524902}, {"id": "UgxsdiL33xMv2-Gl0et4AaABAg", "text": "대한민국 축구는 망했어도  롤은 한국팀이 이겼으면 좋겠다 쉬원쉬원한 한방 기다려집니다", "likeCount": 0, "sentiment": "NEUTRAL", "topic": "팬들의 응원과 기대", "x": -122.41862487792969, "y": -9.585902214050293, "z": 118.28633117675781, "x2d": -160.90640258789062, "y2d": 68.65286254882812}, {"id": "UgxNoEhfyqWAX-cNB4F4AaABAg", "text": "우리 티원 드디어 내일부터 경기 볼 수 있어요!!! 많은 응원 부탁드려요!!!", "likeCount": 0, "sentiment": "POSITIVE", "topic": "팬들의 응원과 기대", "x": -109.41866302490234, "y": -43.42284393310547, "z": 108.56130981445312, "x2d": -156.24642944335938, "y2d": 84.06774139404297}, {"id": "UgxiNFJouAsJj8B9uNJ4AaABAg", "text": "이런 광고 비하인드올리면 광고도 두번되고 우리도 두번행복하고 좋은데요? 광고마다 올려주세요^^^^^^^", "likeCount": 0, "sentiment": "POSITIVE", "topic": "팬들의 응원과 기대", "x": -69.87908935546875, "y": -36.545528411865234, "z": 160.32681274414062, "x2d": -116.94673919677734, "y2d": 121.29883575439453}, {"id": "Ugylm6JBmh-fSwOCehJ4AaABAg.AYYKMmuNgipAYZXI_RSh3i", "text": "예의바른 청년....", "likeCount": 0, "sentiment": "NEUTRAL", "topic": "팬들의 응원과 기대", "x": -20.23471450805664, "y": -111.59590911865234, "z": 32.9935417175293, "x2d": -12.305571556091309, "y2d": -4.158472537994385}], "links": [{"source": "UgxunD7KgIvZaUnJunN4AaABAg", "target": "Ugylm6JBmh-fSwOCehJ4AaABAg", "similarity": 0.436}, {"source": "UgwxPcNmL1joxXd6SoF4AaABAg", "target": "UgzJ4E1Kz4U5xNErlhl4AaABAg", "similarity": 0.438}, {"source": "UgwxPcNmL1joxXd6SoF4AaABAg", "target": "Ugx5cZO-uF1xJuf21IJ4AaABAg", "similarity": 0.591}, {"source": "UgweT1oIFhPYtNQR87B4AaABAg", "target": "UgwxPcNmL1joxXd6SoF4AaABAg", "similarity": 0.717}, {"source": "UgwxPcNmL1joxXd6SoF4AaABAg", "target": "UgxunD7KgIvZaUnJunN4AaABAg.AYYL82QtxYfAYYVatSJ0p3", "similarity": 0.476}, {"source": "Ugy7amkPZzWn50A_74t4AaABAg", "target": "Ugz_2FS16-tAw21maaN4AaABAg", "similarity": 0.506}, {"source": "UgyDH2i_ZLQaXbQrqvl4AaABAg", "target": "Ugz_2FS16-tAw21maaN4AaABAg", "similarity": 0.505}, {"source": "Ugy6MD04XwudtCRotnR4AaABAg", "target": "UgyVJsJ-bJ-S9AiuLzJ4AaABAg", "similarity": 0.477}, {"source": "Ugw4fmlkj69-u3E4MsB4AaABAg", "target": "Ugy6MD04XwudtCRotnR4AaABAg", "similarity": 0.508}, {"source": "UgwKb5EX3cKi5QTzQ_J4AaABAg", "target": "UgyL36JM5mc__ZHz-YZ4AaABAg", "similarity": 0.549}, {"source": "UgwKb5EX3cKi5QTzQ_J4AaABAg", "target": "UgzNkblaPFroQGebaD54AaABAg", "similarity": 0.505}, {"source": "UgwKb5EX3cKi5QTzQ_J4AaABAg", "target": "UgwSj8ZAWxEWiQ5Fcbd4AaABAg", "similarity": 0.588}, {"source": "UgwaKNozKvLPNxQigKF4AaABAg", "target": "Ugx5eF-zgJDyinSqmOp4AaABAg", "similarity": 0.636}, {"source": "Ugx5eF-zgJDyinSqmOp4AaABAg", "target": "UgxnR3UQRpzuinJySF94AaABAg", "similarity": 0.646}, {"source": "UgxeHRPXsYpYwrZggVl4AaABAg", "target": "Ugy1NZdyBmejxLBD9Vl4AaABAg", "similarity": 0.633}, {"source": "Ugw8ATraB1XwJP0t9kB4AaABAg", "target": "UgxeHRPXsYpYwrZggVl4AaABAg", "similarity": 0.486}, {"source": "UgxQnCcpPSJM3GUzTu14AaABAg", "target": "UgxeHRPXsYpYwrZggVl4AaABAg", "similarity": 0.515}, {"source": "Ugy7amkPZzWn50A_74t4AaABAg", "target": "Ugz38AXDlDNyxyfk3nZ4AaABAg", "similarity": 0.599}, {"source": "Ugy7amkPZzWn50A_74t4AaABAg", "target": "UgyRrNPg5G2fCNda2s54AaABAg", "similarity": 0.828}, {"source": "UgxN8ZJhEAK8p7eR0Bt4AaABAg", "target": "UgyhWCw8aB02GXZBEX54AaABAg", "similarity": 0.604}, {"source": "UgyRrNPg5G2fCNda2s54AaABAg", "target": "UgyhWCw8aB02GXZBEX54AaABAg", "similarity": 0.65}, {"source": "UgwaKNozKvLPNxQigKF4AaABAg", "target": "UgyhWCw8aB02GXZBEX54AaABAg", "similarity": 0.571}, {"source": "UgxnR3UQRpzuinJySF94AaABAg", "target": "UgyhWCw8aB02GXZBEX54AaABAg", "similarity": 0.575}, {"source": "UgwhGnW_LZHu9-lh9mp4AaABAg", "target": "Ugy6MD04XwudtCRotnR4AaABAg", "similarity": 0.565}, {"source": "UgwEnjqLSfANyAVu7C94AaABAg", "target": "UgwhGnW_LZHu9-lh9mp4AaABAg", "similarity": 0.527}, {"source": "UgwhGnW_LZHu9-lh9mp4AaABAg", "target": "UgygTA1lLMkLcoi_Jfx4AaABAg", "similarity": 0.493}, {"source": "UgwhGnW_LZHu9-lh9mp4AaABAg", "target": "UgxuushpZ80BPNnIbRl4AaABAg", "similarity": 0.624}, {"source": "UgxuushpZ80BPNnIbRl4AaABAg", "target": "Ugy6MD04XwudtCRotnR4AaABAg", "similarity": 0.512}, {"source": "UgxtFYaajII_TNZLUIN4AaABAg", "target": "Ugz7B1tXPkmqSRNBJ7R4AaABAg", "similarity": 0.487}, {"source": "Ugw3cvLhN1OPEar3AWt4AaABAg", "target": "UgxtFYaajII_TNZLUIN4AaABAg", "similarity": 0.526}, {"source": "UgwNhUq33BC97zLE5CF4AaABAg", "target": "UgxtFYaajII_TNZLUIN4AaABAg", "similarity": 0.737}, {"source": "UgxN8ZJhEAK8p7eR0Bt4AaABAg", "target": "UgyRrNPg5G2fCNda2s54AaABAg", "similarity": 0.658}, {"source": "UgyRrNPg5G2fCNda2s54AaABAg", "target": "Ugz38AXDlDNyxyfk3nZ4AaABAg", "similarity": 0.646}, {"source": "UgxnR3UQRpzuinJySF94AaABAg", "target": "UgyRrNPg5G2fCNda2s54AaABAg", "similarity": 0.564}, {"source": "UgwaKNozKvLPNxQigKF4AaABAg", "target": "UgxN8ZJhEAK8p7eR0Bt4AaABAg", "similarity": 0.629}, {"source": "UgwaKNozKvLPNxQigKF4AaABAg", "target": "UgyL36JM5mc__ZHz-YZ4AaABAg", "similarity": 0.755}, {"source": "UgwSj8ZAWxEWiQ5Fcbd4AaABAg", "target": "UgwaKNozKvLPNxQigKF4AaABAg", "similarity": 0.575}, {"source": "UgwSj8ZAWxEWiQ5Fcbd4AaABAg", "target": "UgyL36JM5mc__ZHz-YZ4AaABAg", "similarity": 0.608}, {"source": "UgwphTJcQfVrF0qBf3d4AaABAg", "target": "UgyO4raLZ6n8L8MheoR4AaABAg", "similarity": 0.498}, {"source": "UgxOY42CNKsMzXcqG5x4AaABAg", "target": "UgzNkblaPFroQGebaD54AaABAg", "similarity": 0.487}, {"source": "UgwSj8ZAWxEWiQ5Fcbd4AaABAg", "target": "UgzNkblaPFroQGebaD54AaABAg", "similarity": 0.503}, {"source": "Ugx5cZO-uF1xJuf21IJ4AaABAg", "target": "Ugy1NZdyBmejxLBD9Vl4AaABAg", "similarity": 0.583}, {"source": "Ugx-sxZXHn3XTe-7sQt4AaABAg", "target": "Ugx5cZO-uF1xJuf21IJ4AaABAg", "similarity": 0.552}, {"source": "Ugx5cZO-uF1xJuf21IJ4AaABAg", "target": "Ugz38AXDlDNyxyfk3nZ4AaABAg", "similarity": 0.601}, {"source": "UgweT1oIFhPYtNQR87B4AaABAg", "target": "Ugx5cZO-uF1xJuf21IJ4AaABAg", "similarity": 0.539}, {"source": "UgzHzYVviNTP3jlPMJF4AaABAg", "target": "Ugzt0frM_nZSNXxNxeJ4AaABAg", "similarity": 0.397}, {"source": "UgwEnjqLSfANyAVu7C94AaABAg", "target": "UgwQ3iv8FU6j7-XY4Nx4AaABAg", "similarity": 0.46}, {"source": "UgwvD7Tnd0xF70Jcwip4AaABAg", "target": "Ugxxvm1lIhgRtbWvPI54AaABAg", "similarity": 0.461}, {"source": "UgwsG9eZLurXdpVU25x4AaABAg", "target": "Ugxxvm1lIhgRtbWvPI54AaABAg", "similarity": 0.424}, {"source": "UgxN8ZJhEAK8p7eR0Bt4AaABAg", "target": "UgxnR3UQRpzuinJySF94AaABAg", "similarity": 0.644}, {"source": "Ugwi0qDHKK1msa5tjH54AaABAg", "target": "UgxnR3UQRpzuinJySF94AaABAg", "similarity": 0.563}, {"source": "UgweT1oIFhPYtNQR87B4AaABAg", "target": "UgxunD7KgIvZaUnJunN4AaABAg.AYYL82QtxYfAYYVatSJ0p3", "similarity": 0.541}, {"source": "UgweT1oIFhPYtNQR87B4AaABAg", "target": "Ugx_wwy1sjBceaYQ6VN4AaABAg", "similarity": 0.447}, {"source": "UgwSj8ZAWxEWiQ5Fcbd4AaABAg", "target": "UgxuushpZ80BPNnIbRl4AaABAg", "similarity": 0.504}, {"source": "UgxunD7KgIvZaUnJunN4AaABAg.AYYL82QtxYfAYYVatSJ0p3", "target": "Ugyehtzy32EcBLa8rHt4AaABAg.AYYX8sWpIWgAYZV5XgVDAm", "similarity": 0.485}, {"source": "Ugx_wwy1sjBceaYQ6VN4AaABAg", "target": "UgzCSg8DA7a5TevTKCN4AaABAg", "similarity": 0.433}, {"source": "Ugw3cvLhN1OPEar3AWt4AaABAg", "target": "Ugx_wwy1sjBceaYQ6VN4AaABAg", "similarity": 0.423}, {"source": "UgxNMymUh0DqE52Y74x4AaABAg", "target": "UgzLpgCGRLV7PTE093Z4AaABAg", "similarity": 0.45}, {"source": "UgzLpgCGRLV7PTE093Z4AaABAg", "target": "UgzpvQ8NKSTH2ffF2XZ4AaABAg", "similarity": 0.494}, {"source": "UgzLpgCGRLV7PTE093Z4AaABAg", "target": "Ugzl_5qQy_TYRj3bXs94AaABAg", "similarity": 0.454}, {"source": "UgxunD7KgIvZaUnJunN4AaABAg.AYYL82QtxYfAYYYS2c5AFw", "target": "UgzLpgCGRLV7PTE093Z4AaABAg", "similarity": 0.565}, {"source": "UgzLpgCGRLV7PTE093Z4AaABAg", "target": "Ugzwbd2FpjF1HGXwhzV4AaABAg", "similarity": 0.518}, {"source": "Ugx_kVj-oQCUFhtd2wB4AaABAg", "target": "UgygTA1lLMkLcoi_Jfx4AaABAg", "similarity": 0.546}, {"source": "UgwFdwLqnU4N6uep6H54AaABAg", "target": "UgwsM7THDKDV78PQrkp4AaABAg", "similarity": 0.455}, {"source": "UgwFdwLqnU4N6uep6H54AaABAg", "target": "Ugz_2FS16-tAw21maaN4AaABAg.AYYOmDN_Go7AYZXaNR4bIx", "similarity": 0.528}, {"source": "Ugw8zzidDQ-_-VfRh0V4AaABAg", "target": "Ugz12RZCsqQUg8Nk3254AaABAg", "similarity": 0.636}, {"source": "UgwqQzvvBzaLM--dErx4AaABAg", "target": "Ugz12RZCsqQUg8Nk3254AaABAg", "similarity": 0.608}, {"source": "UgxUMaVKSLsmhqO8gQ94AaABAg", "target": "Ugz12RZCsqQUg8Nk3254AaABAg", "similarity": 0.558}, {"source": "UgwhqR43PgV0B7nbyRp4AaABAg", "target": "Ugz12RZCsqQUg8Nk3254AaABAg", "similarity": 0.476}, {"source": "UgxQnCcpPSJM3GUzTu14AaABAg", "target": "Ugy1NZdyBmejxLBD9Vl4AaABAg", "similarity": 0.574}, {"source": "Ugy0nNZg2-ac8s0UIgl4AaABAg", "target": "Ugz_2FS16-tAw21maaN4AaABAg.AYYOmDN_Go7AYZXaNR4bIx", "similarity": 0.412}, {"source": "UgxGcHxTFfV83q4KShF4AaABAg", "target": "Ugy0nNZg2-ac8s0UIgl4AaABAg", "similarity": 0.393}, {"source": "UgwiYqxTr2ACDWkIX314AaABAg", "target": "UgzxTXa4nzgMykVPIad4AaABAg", "similarity": 0.379}, {"source": "UgwiYqxTr2ACDWkIX314AaABAg", "target": "UgxCw4FWyGtERh0TmNR4AaABAg", "similarity": 0.485}, {"source": "UgxwB974JG5OFP2znzR4AaABAg", "target": "UgzpvQ8NKSTH2ffF2XZ4AaABAg", "similarity": 0.513}, {"source": "UgzUT9KZgWuT4i9iad14AaABAg", "target": "UgzpvQ8NKSTH2ffF2XZ4AaABAg", "similarity": 0.616}, {"source": "UgzpvQ8NKSTH2ffF2XZ4AaABAg", "target": "Ugzwbd2FpjF1HGXwhzV4AaABAg", "similarity": 0.523}, {"source": "UgxunD7KgIvZaUnJunN4AaABAg.AYYL82QtxYfAYYYS2c5AFw", "target": "UgzpvQ8NKSTH2ffF2XZ4AaABAg", "similarity": 0.544}, {"source": "UgxzFRb-drXn3e9Zyb54AaABAg", "target": "Ugy5uX6gVchQfV6zJ8R4AaABAg", "similarity": 0.416}, {"source": "UgxkV1TC7TFFHRFu8Vd4AaABAg", "target": "Ugzl_5qQy_TYRj3bXs94AaABAg", "similarity": 0.423}, {"source": "UgwSXmbi3qtvCBUjqZh4AaABAg", "target": "Ugykxzs2SsPxkbnjEox4AaABAg", "similarity": 0.557}, {"source": "UgxNMymUh0DqE52Y74x4AaABAg", "target": "UgzUT9KZgWuT4i9iad14AaABAg", "similarity": 0.515}, {"source": "UgxwB974JG5OFP2znzR4AaABAg", "target": "UgzUT9KZgWuT4i9iad14AaABAg", "similarity": 0.673}, {"source": "UgxunD7KgIvZaUnJunN4AaABAg.AYYL82QtxYfAYYYS2c5AFw", "target": "UgzUT9KZgWuT4i9iad14AaABAg", "similarity": 0.513}, {"source": "UgzUT9KZgWuT4i9iad14AaABAg", "target": "Ugzwbd2FpjF1HGXwhzV4AaABAg", "similarity": 0.484}, {"source": "UgxkV1TC7TFFHRFu8Vd4AaABAg", "target": "Ugzwbd2FpjF1HGXwhzV4AaABAg", "similarity": 0.528}, {"source": "UgxuSkhbH7-wXlYppvR4AaABAg", "target": "Ugz_2FS16-tAw21maaN4AaABAg.AYYOmDN_Go7AYZXaNR4bIx", "similarity": 0.429}, {"source": "UgxGcHxTFfV83q4KShF4AaABAg", "target": "Ugz_2FS16-tAw21maaN4AaABAg.AYYOmDN_Go7AYZXaNR4bIx", "similarity": 0.403}, {"source": "UgwqQzvvBzaLM--dErx4AaABAg", "target": "UgxuSkhbH7-wXlYppvR4AaABAg", "similarity": 0.415}, {"source": "Ugw8zzidDQ-_-VfRh0V4AaABAg", "target": "UgwqQzvvBzaLM--dErx4AaABAg", "similarity": 0.641}, {"source": "UgwqQzvvBzaLM--dErx4AaABAg", "target": "Ugwvzqk5x0f474uCI854AaABAg", "similarity": 0.451}, {"source": "Ugzan5cV5I238hvc78t4AaABAg", "target": "Ugzt0frM_nZSNXxNxeJ4AaABAg", "similarity": 0.487}, {"source": "Ugy7g6xghXjLSfz_gI54AaABAg", "target": "UgyY2h3pWUzbgqU1uop4AaABAg", "similarity": 0.385}, {"source": "UgytjGNsxqIV-UpWbdh4AaABAg", "target": "Ugzk5VuWQHto6tjjrkZ4AaABAg", "similarity": 0.36}, {"source": "UgxO0_AzT0icOMCMxHJ4AaABAg", "target": "UgytjGNsxqIV-UpWbdh4AaABAg", "similarity": 0.388}, {"source": "UgxE_7OtYP-nMxzcnPp4AaABAg", "target": "Ugxcouzj4VTqOHskoE14AaABAg", "similarity": 0.462}, {"source": "UgxnT1wRQBzVrzJE8xJ4AaABAg", "target": "UgzxTXa4nzgMykVPIad4AaABAg", "similarity": 0.394}, {"source": "UgxCw4FWyGtERh0TmNR4AaABAg", "target": "UgzxTXa4nzgMykVPIad4AaABAg", "similarity": 0.511}, {"source": "Ugzan5cV5I238hvc78t4AaABAg", "target": "UgzxTXa4nzgMykVPIad4AaABAg", "similarity": 0.373}, {"source": "UgwUf_fmKfrvWpkfXzJ4AaABAg", "target": "UgxGcHxTFfV83q4KShF4AaABAg", "similarity": 0.39}, {"source": "UgwUf_fmKfrvWpkfXzJ4AaABAg", "target": "Ugyehtzy32EcBLa8rHt4AaABAg.AYYX8sWpIWgAYZV5XgVDAm", "similarity": 0.474}, {"source": "Ugyehtzy32EcBLa8rHt4AaABAg", "target": "UgzJ4E1Kz4U5xNErlhl4AaABAg", "similarity": 0.461}, {"source": "Ugwvzqk5x0f474uCI854AaABAg", "target": "UgxwB974JG5OFP2znzR4AaABAg", "similarity": 0.452}, {"source": "UgwphTJcQfVrF0qBf3d4AaABAg", "target": "Ugwvzqk5x0f474uCI854AaABAg", "similarity": 0.577}, {"source": "UgwvD7Tnd0xF70Jcwip4AaABAg", "target": "Ugwvzqk5x0f474uCI854AaABAg", "similarity": 0.538}, {"source": "Ugwvzqk5x0f474uCI854AaABAg", "target": "Ugyat4Pnpw8PthVNved4AaABAg", "similarity": 0.581}, {"source": "Ugw7IuzZQ9kTF2gFxRt4AaABAg", "target": "Ugxy4O5RYKO43V4Wj8l4AaABAg", "similarity": 0.463}, {"source": "Ugw7IuzZQ9kTF2gFxRt4AaABAg", "target": "Ugzk5VuWQHto6tjjrkZ4AaABAg", "similarity": 0.458}, {"source": "UgxuSkhbH7-wXlYppvR4AaABAg", "target": "UgygTA1lLMkLcoi_Jfx4AaABAg", "similarity": 0.501}, {"source": "UgxuushpZ80BPNnIbRl4AaABAg", "target": "UgygTA1lLMkLcoi_Jfx4AaABAg", "similarity": 0.64}, {"source": "Ugxcouzj4VTqOHskoE14AaABAg", "target": "Ugylm6JBmh-fSwOCehJ4AaABAg", "similarity": 0.579}, {"source": "UgzCSg8DA7a5TevTKCN4AaABAg", "target": "UgzxQqC-yJCkQn31j214AaABAg", "similarity": 0.432}, {"source": "UgxN8ZJhEAK8p7eR0Bt4AaABAg", "target": "Ugz38AXDlDNyxyfk3nZ4AaABAg", "similarity": 0.619}, {"source": "UgxuSkhbH7-wXlYppvR4AaABAg", "target": "UgzCSg8DA7a5TevTKCN4AaABAg", "similarity": 0.456}, {"source": "UgxuSkhbH7-wXlYppvR4AaABAg", "target": "Ugyat4Pnpw8PthVNved4AaABAg", "similarity": 0.416}, {"source": "Ugwi0qDHKK1msa5tjH54AaABAg", "target": "Ugz7B1tXPkmqSRNBJ7R4AaABAg", "similarity": 0.466}, {"source": "Ugz2fdNQN2yjS5KaQu14AaABAg", "target": "Ugz7B1tXPkmqSRNBJ7R4AaABAg", "similarity": 0.722}, {"source": "Ugxcouzj4VTqOHskoE14AaABAg", "target": "Ugz7B1tXPkmqSRNBJ7R4AaABAg", "similarity": 0.455}, {"source": "Ugw8ATraB1XwJP0t9kB4AaABAg", "target": "UgxQnCcpPSJM3GUzTu14AaABAg", "similarity": 0.429}, {"source": "Ugw8ATraB1XwJP0t9kB4AaABAg", "target": "UgxeDMHRYyoFlqOqlzx4AaABAg", "similarity": 0.457}, {"source": "Ugw3cvLhN1OPEar3AWt4AaABAg", "target": "UgwNhUq33BC97zLE5CF4AaABAg", "similarity": 0.529}, {"source": "UgwQ3iv8FU6j7-XY4Nx4AaABAg", "target": "UgxxJMY_O3fdw4aHB0R4AaABAg", "similarity": 0.44}, {"source": "Ugx-sxZXHn3XTe-7sQt4AaABAg", "target": "Ugz38AXDlDNyxyfk3nZ4AaABAg", "similarity": 0.621}, {"source": "UgxO0_AzT0icOMCMxHJ4AaABAg", "target": "Ugxy4O5RYKO43V4Wj8l4AaABAg", "similarity": 0.386}, {"source": "UgxO0_AzT0icOMCMxHJ4AaABAg", "target": "Ugzk5VuWQHto6tjjrkZ4AaABAg", "similarity": 0.402}, {"source": "UgwAKJBVgA9k-mtBsDd4AaABAg", "target": "UgyxmwQr4geDW7xfTDV4AaABAg", "similarity": 0.399}, {"source": "UgyxmwQr4geDW7xfTDV4AaABAg", "target": "UgzqFJuUIp084Qp_qJV4AaABAg", "similarity": 0.395}, {"source": "UgxntCqXb7tHCgWM7Yp4AaABAg", "target": "UgyCM-iJa2VOF-4E5oR4AaABAg", "similarity": 0.353}, {"source": "UgxiNFJouAsJj8B9uNJ4AaABAg", "target": "UgxntCqXb7tHCgWM7Yp4AaABAg", "similarity": 0.43}, {"source": "UgwAKJBVgA9k-mtBsDd4AaABAg", "target": "UgxSpjY54tkwfzBc-Rp4AaABAg", "similarity": 0.585}, {"source": "UgwAKJBVgA9k-mtBsDd4AaABAg", "target": "UgwL1HhownC9iBVTpsB4AaABAg", "similarity": 0.476}, {"source": "UgwAKJBVgA9k-mtBsDd4AaABAg", "target": "UgytaolXcMzl0gHH53V4AaABAg", "similarity": 0.422}, {"source": "UgwAKJBVgA9k-mtBsDd4AaABAg", "target": "UgyapM85D1oEpTr0W2h4AaABAg", "similarity": 0.606}, {"source": "UgwL1HhownC9iBVTpsB4AaABAg", "target": "UgyUaU5ztMeLynRVpZ94AaABAg", "similarity": 0.592}, {"source": "UgyUaU5ztMeLynRVpZ94AaABAg", "target": "UgyapM85D1oEpTr0W2h4AaABAg", "similarity": 0.482}, {"source": "Ugxy4O5RYKO43V4Wj8l4AaABAg", "target": "Ugzk5VuWQHto6tjjrkZ4AaABAg", "similarity": 0.478}, {"source": "UgwphTJcQfVrF0qBf3d4AaABAg", "target": "UgwvD7Tnd0xF70Jcwip4AaABAg", "similarity": 0.441}, {"source": "UgwphTJcQfVrF0qBf3d4AaABAg", "target": "UgwsG9eZLurXdpVU25x4AaABAg", "similarity": 0.449}, {"source": "UgwphTJcQfVrF0qBf3d4AaABAg", "target": "Ugyat4Pnpw8PthVNved4AaABAg", "similarity": 0.455}, {"source": "UgwvD7Tnd0xF70Jcwip4AaABAg", "target": "UgyCM-iJa2VOF-4E5oR4AaABAg", "similarity": 0.402}, {"source": "UgxunD7KgIvZaUnJunN4AaABAg.AYYL82QtxYfAYYYS2c5AFw", "target": "UgxwB974JG5OFP2znzR4AaABAg", "similarity": 0.451}, {"source": "UgxNMymUh0DqE52Y74x4AaABAg", "target": "UgxwB974JG5OFP2znzR4AaABAg", "similarity": 0.497}, {"source": "UgxsdiL33xMv2-Gl0et4AaABAg", "target": "UgyVUJKmygQmQ5QCjzt4AaABAg", "similarity": 0.353}, {"source": "UgyVUJKmygQmQ5QCjzt4AaABAg", "target": "Ugymib8qOfFalJCdzP14AaABAg", "similarity": 0.463}, {"source": "UgxNoEhfyqWAX-cNB4F4AaABAg", "target": "UgyEGCPnl9m7HEsruHp4AaABAg", "similarity": 0.588}, {"source": "UgyEGCPnl9m7HEsruHp4AaABAg", "target": "Ugymib8qOfFalJCdzP14AaABAg", "similarity": 0.471}, {"source": "UgyEGCPnl9m7HEsruHp4AaABAg", "target": "Ugz6fBDAWfcB0d4Ca4R4AaABAg", "similarity": 0.606}, {"source": "UgwL1HhownC9iBVTpsB4AaABAg", "target": "UgxSpjY54tkwfzBc-Rp4AaABAg", "similarity": 0.499}, {"source": "UgwhqR43PgV0B7nbyRp4AaABAg", "target": "UgxSpjY54tkwfzBc-Rp4AaABAg", "similarity": 0.465}, {"source": "UgxSpjY54tkwfzBc-Rp4AaABAg", "target": "UgytaolXcMzl0gHH53V4AaABAg", "similarity": 0.562}, {"source": "UgxSpjY54tkwfzBc-Rp4AaABAg", "target": "UgyapM85D1oEpTr0W2h4AaABAg", "similarity": 0.626}, {"source": "UgxNoEhfyqWAX-cNB4F4AaABAg", "target": "Ugz6fBDAWfcB0d4Ca4R4AaABAg", "similarity": 0.622}, {"source": "UgxUMaVKSLsmhqO8gQ94AaABAg", "target": "Ugz6fBDAWfcB0d4Ca4R4AaABAg", "similarity": 0.493}, {"source": "Ugz6fBDAWfcB0d4Ca4R4AaABAg", "target": "UgzhM4AEN99MqWqKWJN4AaABAg", "similarity": 0.606}, {"source": "UgxbXd30QKKOsfio_bR4AaABAg", "target": "Ugz6fBDAWfcB0d4Ca4R4AaABAg", "similarity": 0.606}, {"source": "Ugylm6JBmh-fSwOCehJ4AaABAg.AYYKMmuNgipAYYMWH3OaH7", "target": "UgytaolXcMzl0gHH53V4AaABAg", "similarity": 0.389}, {"source": "Ugw8zzidDQ-_-VfRh0V4AaABAg", "target": "UgxUMaVKSLsmhqO8gQ94AaABAg", "similarity": 0.526}, {"source": "UgxUMaVKSLsmhqO8gQ94AaABAg", "target": "UgzhM4AEN99MqWqKWJN4AaABAg", "similarity": 0.481}, {"source": "UgxUMaVKSLsmhqO8gQ94AaABAg", "target": "UgxbXd30QKKOsfio_bR4AaABAg", "similarity": 0.481}, {"source": "UgwQ3iv8FU6j7-XY4Nx4AaABAg", "target": "Ugxcouzj4VTqOHskoE14AaABAg", "similarity": 0.457}, {"source": "UgxgiNLY-mfepiSTSCh4AaABAg", "target": "UgzhM4AEN99MqWqKWJN4AaABAg", "similarity": 0.488}, {"source": "UgxbXd30QKKOsfio_bR4AaABAg", "target": "UgxgiNLY-mfepiSTSCh4AaABAg", "similarity": 0.488}, {"source": "UgxNoEhfyqWAX-cNB4F4AaABAg", "target": "UgyqNTaVzey-NzaP2Rh4AaABAg", "similarity": 0.488}, {"source": "Ugx0N8Ps0cvF59bKrhl4AaABAg", "target": "UgzSIlJO4Y48x1TpHJh4AaABAg", "similarity": 0.356}, {"source": "UgwL1HhownC9iBVTpsB4AaABAg", "target": "UgytaolXcMzl0gHH53V4AaABAg", "similarity": 0.534}, {"source": "UgwL1HhownC9iBVTpsB4AaABAg", "target": "UgyapM85D1oEpTr0W2h4AaABAg", "similarity": 0.638}, {"source": "UgwhqR43PgV0B7nbyRp4AaABAg", "target": "UgzqFJuUIp084Qp_qJV4AaABAg", "similarity": 0.415}, {"source": "UgyapM85D1oEpTr0W2h4AaABAg", "target": "UgytaolXcMzl0gHH53V4AaABAg", "similarity": 0.514}, {"source": "Ugw8zzidDQ-_-VfRh0V4AaABAg", "target": "UgzhM4AEN99MqWqKWJN4AaABAg", "similarity": 0.509}, {"source": "UgxbXd30QKKOsfio_bR4AaABAg", "target": "UgzhM4AEN99MqWqKWJN4AaABAg", "similarity": 1.0}, {"source": "Ugw8zzidDQ-_-VfRh0V4AaABAg", "target": "UgxbXd30QKKOsfio_bR4AaABAg", "similarity": 0.509}]}