{
  "video": {
    "videoId": "piORpJO4lDU",
    "title": "해변가 파티 이상혁 The Red Sea Ep.1",
    "channelTitle": "T1",
    "thumbnailUrl": "https://i.ytimg.com/vi/piORpJO4lDU/maxresdefault.jpg",
    "publishedAt": "2025-12-30",
    "viewCount": 522672,
    "likeCount": 15487,
    "analyzedComments": 939,
    "languageRatio": {
      "ko": 88,
      "en": 5,
      "other": 7
    },
    "weightedSentiment": 81
  },
  "topics": [
    {
      "label": "페이커의 매력",
      "labelEn": "Faker's Charm",
      "labelZh": "Faker的魅力",
      "labelJa": "フェイカーの魅力",
      "mentionCount": 336,
      "sentiment": {
        "positive": 76,
        "neutral": 21,
        "negative": 3
      }
    },
    {
      "label": "선수들의 즐거움",
      "labelEn": "Players' Enjoyment",
      "labelZh": "球员的乐趣",
      "labelJa": "選手の楽しみ",
      "mentionCount": 293,
      "sentiment": {
        "positive": 73,
        "neutral": 23,
        "negative": 4
      }
    },
    {
      "label": "팀워크",
      "labelEn": "Teamwork",
      "labelZh": "团队合作",
      "labelJa": "チームワーク",
      "mentionCount": 183,
      "sentiment": {
        "positive": 51,
        "neutral": 44,
        "negative": 5
      }
    },
    {
      "label": "편집 스타일",
      "labelEn": "Editing Style",
      "labelZh": "编辑风格",
      "labelJa": "編集スタイル",
      "mentionCount": 95,
      "sentiment": {
        "positive": 45,
        "neutral": 48,
        "negative": 6
      }
    },
    {
      "label": "게임과 휴식의 균형",
      "labelEn": "Balance of Gaming and Relaxation",
      "labelZh": "游戏与休息的平衡",
      "labelJa": "ゲームと休息のバランス",
      "mentionCount": 32,
      "sentiment": {
        "positive": 72,
        "neutral": 19,
        "negative": 9
      }
    }
  ],
  "reactionTimeline": [
    {
      "elapsedSeconds": 18121.0,
      "bucketStart": "2025-12-30T05:02:01+00:00",
      "bucketEnd": "2025-12-30T05:06:00+00:00",
      "positive": 20,
      "neutral": 19,
      "negative": 1,
      "netSentiment": 0.475,
      "zScore": -1.474,
      "isBurst": false,
      "direction": null
    },
    {
      "elapsedSeconds": 18362.0,
      "bucketStart": "2025-12-30T05:06:02+00:00",
      "bucketEnd": "2025-12-30T05:13:23+00:00",
      "positive": 26,
      "neutral": 12,
      "negative": 2,
      "netSentiment": 0.6,
      "zScore": -0.228,
      "isBurst": false,
      "direction": null
    },
    {
      "elapsedSeconds": 18911.0,
      "bucketStart": "2025-12-30T05:15:11+00:00",
      "bucketEnd": "2025-12-30T05:25:48+00:00",
      "positive": 24,
      "neutral": 13,
      "negative": 3,
      "netSentiment": 0.525,
      "zScore": -0.976,
      "isBurst": false,
      "direction": null
    },
    {
      "elapsedSeconds": 19562.0,
      "bucketStart": "2025-12-30T05:26:02+00:00",
      "bucketEnd": "2025-12-30T05:37:26+00:00",
      "positive": 23,
      "neutral": 13,
      "negative": 4,
      "netSentiment": 0.475,
      "zScore": -1.474,
      "isBurst": false,
      "direction": null
    },
    {
      "elapsedSeconds": 20256.0,
      "bucketStart": "2025-12-30T05:37:36+00:00",
      "bucketEnd": "2025-12-30T05:46:47+00:00",
      "positive": 27,
      "neutral": 12,
      "negative": 1,
      "netSentiment": 0.65,
      "zScore": 0.271,
      "isBurst": false,
      "direction": null
    },
    {
      "elapsedSeconds": 20827.0,
      "bucketStart": "2025-12-30T05:47:07+00:00",
      "bucketEnd": "2025-12-30T05:58:25+00:00",
      "positive": 27,
      "neutral": 13,
      "negative": 0,
      "netSentiment": 0.675,
      "zScore": 0.52,
      "isBurst": false,
      "direction": null
    },
    {
      "elapsedSeconds": 21517.0,
      "bucketStart": "2025-12-30T05:58:37+00:00",
      "bucketEnd": "2025-12-30T06:12:11+00:00",
      "positive": 29,
      "neutral": 10,
      "negative": 1,
      "netSentiment": 0.7,
      "zScore": 0.77,
      "isBurst": false,
      "direction": null
    },
    {
      "elapsedSeconds": 22362.0,
      "bucketStart": "2025-12-30T06:12:42+00:00",
      "bucketEnd": "2025-12-30T06:28:58+00:00",
      "positive": 28,
      "neutral": 11,
      "negative": 1,
      "netSentiment": 0.675,
      "zScore": 0.52,
      "isBurst": false,
      "direction": null
    },
    {
      "elapsedSeconds": 23344.0,
      "bucketStart": "2025-12-30T06:29:04+00:00",
      "bucketEnd": "2025-12-30T06:46:11+00:00",
      "positive": 26,
      "neutral": 8,
      "negative": 6,
      "netSentiment": 0.5,
      "zScore": -1.225,
      "isBurst": false,
      "direction": null
    },
    {
      "elapsedSeconds": 24432.0,
      "bucketStart": "2025-12-30T06:47:12+00:00",
      "bucketEnd": "2025-12-30T07:08:56+00:00",
      "positive": 30,
      "neutral": 8,
      "negative": 2,
      "netSentiment": 0.7,
      "zScore": 0.77,
      "isBurst": false,
      "direction": null
    },
    {
      "elapsedSeconds": 25800.0,
      "bucketStart": "2025-12-30T07:10:00+00:00",
      "bucketEnd": "2025-12-30T07:45:54+00:00",
      "positive": 30,
      "neutral": 7,
      "negative": 3,
      "netSentiment": 0.675,
      "zScore": 0.52,
      "isBurst": false,
      "direction": null
    },
    {
      "elapsedSeconds": 27976.0,
      "bucketStart": "2025-12-30T07:46:16+00:00",
      "bucketEnd": "2025-12-30T08:25:21+00:00",
      "positive": 25,
      "neutral": 14,
      "negative": 1,
      "netSentiment": 0.6,
      "zScore": -0.228,
      "isBurst": false,
      "direction": null
    },
    {
      "elapsedSeconds": 30382.0,
      "bucketStart": "2025-12-30T08:26:22+00:00",
      "bucketEnd": "2025-12-30T09:00:57+00:00",
      "positive": 27,
      "neutral": 11,
      "negative": 2,
      "netSentiment": 0.625,
      "zScore": 0.022,
      "isBurst": false,
      "direction": null
    },
    {
      "elapsedSeconds": 32460.0,
      "bucketStart": "2025-12-30T09:01:00+00:00",
      "bucketEnd": "2025-12-30T09:48:29+00:00",
      "positive": 30,
      "neutral": 8,
      "negative": 2,
      "netSentiment": 0.7,
      "zScore": 0.77,
      "isBurst": false,
      "direction": null
    },
    {
      "elapsedSeconds": 35375.0,
      "bucketStart": "2025-12-30T09:49:35+00:00",
      "bucketEnd": "2025-12-30T10:30:09+00:00",
      "positive": 29,
      "neutral": 8,
      "negative": 3,
      "netSentiment": 0.65,
      "zScore": 0.271,
      "isBurst": false,
      "direction": null
    },
    {
      "elapsedSeconds": 37821.0,
      "bucketStart": "2025-12-30T10:30:21+00:00",
      "bucketEnd": "2025-12-30T11:36:05+00:00",
      "positive": 31,
      "neutral": 8,
      "negative": 1,
      "netSentiment": 0.75,
      "zScore": 1.268,
      "isBurst": false,
      "direction": null
    },
    {
      "elapsedSeconds": 41802.0,
      "bucketStart": "2025-12-30T11:36:42+00:00",
      "bucketEnd": "2025-12-30T13:02:40+00:00",
      "positive": 32,
      "neutral": 6,
      "negative": 2,
      "netSentiment": 0.75,
      "zScore": 1.268,
      "isBurst": false,
      "direction": null
    },
    {
      "elapsedSeconds": 47230.0,
      "bucketStart": "2025-12-30T13:07:10+00:00",
      "bucketEnd": "2025-12-30T14:52:55+00:00",
      "positive": 24,
      "neutral": 16,
      "negative": 0,
      "netSentiment": 0.6,
      "zScore": -0.228,
      "isBurst": false,
      "direction": null
    },
    {
      "elapsedSeconds": 54305.0,
      "bucketStart": "2025-12-30T15:05:05+00:00",
      "bucketEnd": "2025-12-30T18:12:03+00:00",
      "positive": 28,
      "neutral": 11,
      "negative": 1,
      "netSentiment": 0.675,
      "zScore": 0.52,
      "isBurst": false,
      "direction": null
    },
    {
      "elapsedSeconds": 66732.0,
      "bucketStart": "2025-12-30T18:32:12+00:00",
      "bucketEnd": "2025-12-31T04:15:29+00:00",
      "positive": 29,
      "neutral": 10,
      "negative": 1,
      "netSentiment": 0.7,
      "zScore": 0.77,
      "isBurst": false,
      "direction": null
    },
    {
      "elapsedSeconds": 101752.0,
      "bucketStart": "2025-12-31T04:15:52+00:00",
      "bucketEnd": "2025-12-31T13:52:14+00:00",
      "positive": 30,
      "neutral": 8,
      "negative": 2,
      "netSentiment": 0.7,
      "zScore": 0.77,
      "isBurst": false,
      "direction": null
    },
    {
      "elapsedSeconds": 138688.0,
      "bucketStart": "2025-12-31T14:31:28+00:00",
      "bucketEnd": "2026-01-04T13:07:47+00:00",
      "positive": 25,
      "neutral": 13,
      "negative": 2,
      "netSentiment": 0.575,
      "zScore": -0.477,
      "isBurst": false,
      "direction": null
    },
    {
      "elapsedSeconds": 483557.0,
      "bucketStart": "2026-01-04T14:19:17+00:00",
      "bucketEnd": "2026-01-19T03:41:14+00:00",
      "positive": 15,
      "neutral": 24,
      "negative": 1,
      "netSentiment": 0.35,
      "zScore": -2.721,
      "isBurst": true,
      "direction": "NEGATIVE_SPIKE",
      "topComments": [
        {
          "text": "2편은 대체 언제나와",
          "likeCount": 26,
          "sentiment": "NEUTRAL"
        },
        {
          "text": "에피 2 언제나와!!!!!",
          "likeCount": 4,
          "sentiment": "NEUTRAL"
        },
        {
          "text": "편집퀄 너무 좋은데??? 누굴 영입한거지??????",
          "likeCount": 3,
          "sentiment": "POSITIVE"
        },
        {
          "text": "15:18 상혁이 운동 많이 된다\n스트레스 많이 받을거야\n근데 그런 스트레스도 필요해\n사우디 레드시 스트롱맨이야",
          "likeCount": 3,
          "sentiment": "NEUTRAL"
        },
        {
          "text": "2편 언제....??",
          "likeCount": 2,
          "sentiment": "NEUTRAL"
        },
        {
          "text": "2편 주세요..",
          "likeCount": 2,
          "sentiment": "NEUTRAL"
        },
        {
          "text": "2편 언제 올리냐",
          "likeCount": 2,
          "sentiment": "NEUTRAL"
        },
        {
          "text": "에피2 원해요",
          "likeCount": 2,
          "sentiment": "NEUTRAL"
        },
        {
          "text": "똑똑...2편은...나오는거죠오오??",
          "likeCount": 2,
          "sentiment": "NEUTRAL"
        },
        {
          "text": "2편 언제 나와요?",
          "likeCount": 2,
          "sentiment": "NEUTRAL"
        },
        {
          "text": "13:45 겁나 웃기넼ㅋㅋㅋㅋㅋㅋㅋㅋㅋㅋㅋㅋㅋㅋㅋ",
          "likeCount": 2,
          "sentiment": "POSITIVE"
        },
        {
          "text": "Next Episode please 🥺",
          "likeCount": 2,
          "sentiment": "NEUTRAL"
        },
        {
          "text": "Peyz is really shy and doran takes good care of him",
          "likeCount": 1,
          "sentiment": "POSITIVE"
        },
        {
          "text": "Part2 plssss",
          "likeCount": 1,
          "sentiment": "NEUTRAL"
        },
        {
          "text": "DROP THE PART 2",
          "likeCount": 1,
          "sentiment": "NEUTRAL"
        },
        {
          "text": "이제 숨 쉴게요",
          "likeCount": 1,
          "sentiment": "NEUTRAL"
        },
        {
          "text": "16:07 ㅋㅋㅋㅋㅋㅋㅋㅋㅋㅋㅋㅋㅋㅋㅋㅋ개웃기넼ㅋㅋㅋㅋㅋ",
          "likeCount": 1,
          "sentiment": "POSITIVE"
        },
        {
          "text": "이거 다음편은 대체 언제?",
          "likeCount": 1,
          "sentiment": "NEUTRAL"
        },
        {
          "text": "23:03 sir?..yes.... 무한반복^^!",
          "likeCount": 1,
          "sentiment": "POSITIVE"
        },
        {
          "text": "2편 까먹은듯",
          "likeCount": 1,
          "sentiment": "NEUTRAL"
        },
        {
          "text": "9일이 지났는데 2편 주세요... LCK컵 시작 전엔 나와야하는거 아닌가요? 😢 이러다 예고편이 끝인건가.... 허허허...",
          "likeCount": 1,
          "sentiment": "NEGATIVE"
        },
        {
          "text": "이야..관상부터 롤악귀라고 써있노",
          "likeCount": 0,
          "sentiment": "NEUTRAL"
        },
        {
          "text": "ㅠㅠ이런 모습 보면 아직 애기들인데 경기만 뛰면 포스가 생기니 반하지",
          "likeCount": 0,
          "sentiment": "POSITIVE"
        },
        {
          "text": "수영장파티 신상혁;;;",
          "likeCount": 0,
          "sentiment": "NEUTRAL"
        },
        {
          "text": "15:45 아니 이거 타는거 이름이 시밥이었잖아 ㅋㄱㅋㄱㅋㄱㄱㅋ",
          "likeCount": 0,
          "sentiment": "POSITIVE"
        },
        {
          "text": "오너 영상 찍는 거 왤케 기특해보이냐 ㅋㅋ",
          "likeCount": 0,
          "sentiment": "POSITIVE"
        },
        {
          "text": "이거 2편 언제 나와여…?",
          "likeCount": 0,
          "sentiment": "NEUTRAL"
        },
        {
          "text": "민석이 무조건 반사적으로 튀어나오는 대답이 ㅈㄴ 웃기네\n페 : 아침에 테니스 치실분\n케 : 진짜 자요",
          "likeCount": 0,
          "sentiment": "POSITIVE"
        },
        {
          "text": "9:11 테토남 케리아",
          "likeCount": 0,
          "sentiment": "NEUTRAL"
        },
        {
          "text": "16:45 \"Ok, let's get it\" LOL",
          "likeCount": 0,
          "sentiment": "POSITIVE"
        },
        {
          "text": "다음편 언제올라와유ㅠㅠㅠ 본거 또보고 또보고 반복중입니다.. 하고 계시겠지만 조금만 더 빨리 부탁드려요..",
          "likeCount": 0,
          "sentiment": "POSITIVE"
        },
        {
          "text": "When is part 2 coming out???",
          "likeCount": 0,
          "sentiment": "NEUTRAL"
        },
        {
          "text": "There's so much B-rolls of young posh i love it",
          "likeCount": 0,
          "sentiment": "POSITIVE"
        },
        {
          "text": "5:55 6:16",
          "likeCount": 0,
          "sentiment": "NEUTRAL"
        },
        {
          "text": "Love them enjoying the beach",
          "likeCount": 0,
          "sentiment": "POSITIVE"
        },
        {
          "text": "2편은 LCK컵 전에 올라오겠죠???😢 예고편의 T1 보고싶어요…",
          "likeCount": 0,
          "sentiment": "NEUTRAL"
        },
        {
          "text": "Roger Fakerer HAHA",
          "likeCount": 0,
          "sentiment": "POSITIVE"
        },
        {
          "text": "هذا وين بالضبط ؟",
          "likeCount": 0,
          "sentiment": "NEUTRAL"
        },
        {
          "text": "3:07 밍식 눈 요리조리 굴리는 거 귀여움....",
          "likeCount": 0,
          "sentiment": "POSITIVE"
        },
        {
          "text": "feel like Peyz and Doran are so out of their comfort zone XD",
          "likeCount": 0,
          "sentiment": "NEUTRAL"
        }
      ]
    }
  ],
  "keyInsights": [
    {
      "type": "positive",
      "topic": "게임과 휴식의 균형",
      "topicEn": "Balance of Gaming and Relaxation",
      "topicZh": "游戏与休息的平衡",
      "topicJa": "ゲームと休息のバランス",
      "comment": "드디어 기어나왔구나 ㅠ",
      "commentLang": "ko",
      "likes": 3050
    },
    {
      "type": "negative",
      "topic": "페이커의 매력",
      "topicEn": "Faker's Charm",
      "topicZh": "Faker的魅力",
      "topicJa": "フェイカーの魅力",
      "comment": "티원이 만들수 있는 영상퀄이 아닌데?",
      "commentLang": "ko",
      "likes": 167
    },
    {
      "type": "positive",
      "topic": "팀워크",
      "topicEn": "Teamwork",
      "topicZh": "团队合作",
      "topicJa": "チームワーク",
      "comment": "페이커 보니까 은근 멤버 다 챙겨주려고 하고 엄청 적극적이네ㅋㅋㅋㅋㅋ 리더맞다",
      "commentLang": "ko",
      "likes": 1760
    },
    {
      "type": "negative",
      "topic": "팀워크",
      "topicEn": "Teamwork",
      "topicZh": "团队合作",
      "topicJa": "チームワーク",
      "comment": "t1영상팀들은 사우디갔다왔을때 부터 지금까지 출근해서 뭐했는지 진술서 써내라 얘들이야 말로 진짜 대기업에서 한다는 마우스 15분이상 안움직이면 사유서 내고 이런걸 해야됨 개인 메신저 사용금지에",
      "commentLang": "ko",
      "likes": 15
    }
  ],
  "analyzedAt": "2026-07-02T15:57:07.438250+00:00",
  "analysisDuration": 160.3,
  "tokenUsage": {
    "input": 42870,
    "output": 11315,
    "embedding": 29844,
    "total": 84029,
    "estimatedCostUsd": 0.013816
  }
}